Workbook

Sheet Summary
A1: Rent vs Buy: Summary
A2: All values update from the Inputs sheet. Net worth is measured as if you sold in the horizon year.
A4: Verdict | B4: =IF(Inputs!$B$47=1,IF(B6>=0,"Buying leaves you ahead by "&TEXT(B6,"$#,##0")&" after "&Inputs!$B$30&" years","Renting and investing leaves you ahead by "&TEXT(-B6,"$#,##0")&" after "&Inputs!$B$30&" years"),"Set filing status (Single or Joint) on the Inputs sheet to see results") -> Buying leaves you ahead by $235,389 after 30 years
A5: Years Until You Sell | B5: =Inputs!$B$30 -> 30
A6: Buy Minus Rent (Future Dollars) | B6: =IF(Inputs!$B$47=1,B7-B8,"-") -> 235389.08 | D6: Positive favors buying.
A7: Buy: Net Worth at Sale | B7: =IF(Inputs!$B$47=1,INDEX(Annual!$V$2:$V$51,B5),"-") -> 1595738.5 | D7: Home value minus selling costs, loan balance, and tax on gain above the exclusion, plus the owner's invested surplus after tax.
A8: Rent: Net Worth at Sale | B8: =IF(Inputs!$B$47=1,INDEX(Annual!$W$2:$W$51,B5),"-") -> 1360349.5 | D8: Renter's portfolio (down payment + closing costs + monthly savings, compounded) after capital gains tax.
A9: Buy Minus Rent (Today's Dollars) | B9: =IF(Inputs!$B$47=1,INDEX(Annual!$Z$2:$Z$51,B5),"-") -> 102799.94
A10: Buying Ahead for Good Starting in Year | B10: =IF(Inputs!$B$47<>1,"-",IF(COUNT(Annual!$AA$2:$AA$51)=0,"Not within 50 years",MIN(Annual!$AA$2:$AA$51))) -> 13 | D10: First year after which buying stays ahead through year 50.
A12: The Mortgage (Full Term)
A13: Loan Amount | B13: =Inputs!$B$39 -> 400000
A14: Monthly Principal and Interest | B14: =Inputs!$B$41 -> 2736.8491
A15: Total Principal Paid | B15: =SUM(Monthly!$E$2:$E$601) -> 400000
A16: Total Interest Paid | B16: =SUM(Monthly!$D$2:$D$601) -> 585265.69
A17: Total Paid to the Lender | B17: =B15+B16 -> 985265.69
A18: Interest per $1 Borrowed | B18: =IF(B13>0,B16/B13,0) -> 1.4631642
A19: Total PMI Paid | B19: =SUM(Monthly!$G$2:$G$601) -> 0
A20: Months with PMI | B20: =COUNTIF(Monthly!$G$2:$G$601,">0") -> 0
A22: First-Year Average Month | B22: Buy | C22: Rent
A23: Principal and Interest | B23: =(Annual!C2+Annual!D2)/12 -> 2736.8491
A24: Property Tax, Insurance, Maintenance, HOA | B24: =SUM(Monthly!I2:L13)/12 -> 1000
A25: PMI | B25: =SUM(Monthly!G2:G13)/12 -> 0
A26: Tax Savings from Itemizing | B26: =-Annual!N2/12 -> 0
A27: All-in Monthly Cost | B27: =Annual!O2/12 -> 3736.8491 | C27: =Annual!P2/12 -> 2515
A28: Difference Invested Each Month (Renter if Positive) | B28: =B27-C27 -> 1221.8491
A30: Money You Don't Get Back, Through the Sale Year (Future Dollars) | B30: Buy | C30: Rent
A31: Mortgage Interest | B31: =SUMIF(Monthly!$A$2:$A$601,"<="&$B$5*12,Monthly!$D$2:$D$601) -> 585265.69
A32: Property Tax | B32: =SUMIF(Monthly!$A$2:$A$601,"<="&$B$5*12,Monthly!$I$2:$I$601) -> 252382.22
A33: Homeowners Insurance | B33: =SUMIF(Monthly!$A$2:$A$601,"<="&$B$5*12,Monthly!$J$2:$J$601) -> 115158.78
A34: Maintenance and Repairs | B34: =SUMIF(Monthly!$A$2:$A$601,"<="&$B$5*12,Monthly!$K$2:$K$601) -> 230317.56
A35: HOA Dues | B35: =SUMIF(Monthly!$A$2:$A$601,"<="&$B$5*12,Monthly!$L$2:$L$601) -> 0
A36: PMI | B36: =SUMIF(Monthly!$A$2:$A$601,"<="&$B$5*12,Monthly!$G$2:$G$601) -> 0
A37: Closing Costs at Purchase | B37: =Inputs!$B$40 -> 12500
A38: Selling Costs at Sale | B38: =INDEX(Annual!$S$2:$S$51,$B$5) -> 97301.925
A39: Tax on Home Gain | B39: =INDEX(Annual!$T$2:$T$51,$B$5) -> 76784.524
A40: Tax Savings from Itemizing | B40: =-SUMIF(Monthly!$A$2:$A$601,"<="&$B$5*12,Monthly!$M$2:$M$601) -> 0
A41: Tax on Dividends While Invested | B41: =SUMIF(Monthly!$A$2:$A$601,"<="&$B$5*12,Monthly!$V$2:$V$601) -> 968.28165 | C41: =SUMIF(Monthly!$A$2:$A$601,"<="&$B$5*12,Monthly!$U$2:$U$601) -> 31683.066
A42: Rent and Renter's Insurance | C42: =SUMIF(Monthly!$A$2:$A$601,"<="&$B$5*12,Monthly!$O$2:$O$601) -> 1556971.8
A43: Total Unrecoverable | B43: =SUM(B31:B42) -> 1370679 | C43: =SUM(C31:C42) -> 1588654.8
A46: Sensitivity, Single filer, DEFAULT inputs only (static values, not live): buy minus rent after 30 years
A47: Computed with the same logic by the Python reference model. Rows = home appreciation, columns = investment return. Use the web version for a live grid, or change Inputs B17/B18 here and read B6.
B48: 0.04 | C48: 0.05 | D48: 0.06 | E48: 0.07 | F48: 0.08 | G48: 0.09 | H48: 0.1
A49: 0.02 | B49: 418503 | C49: 252213 | D49: 35018 | E49: -247726 | F49: -614708 | G49: -1089729 | H49: -1703045
A50: 0.03 | B50: 620994 | C50: 450542 | D50: 228561 | E50: -59700 | F50: -433057 | G50: -915461 | H50: -1537347
A51: 0.04 | B51: 894949 | C51: 719767 | D51: 492370 | E51: 197889 | F51: -182628 | G51: -673295 | H51: -1304735
A52: 0.05 | B52: 1263364 | C52: 1082793 | D52: 849248 | E52: 547735 | F52: 159152 | G52: -340784 | H52: -982906
A53: 0.06 | B53: 1756182 | C53: 1569455 | D53: 1328913 | E53: 1019426 | F53: 621735 | G53: 111367 | H53: -542730
A56: Sensitivity, Joint filer, DEFAULT inputs only (static values, not live): buy minus rent after 30 years
A57: Computed with the same logic by the Python reference model. Rows = home appreciation, columns = investment return. Use the web version for a live grid, or change Inputs B17/B18 here and read B6.
B58: 0.04 | C58: 0.05 | D58: 0.06 | E58: 0.07 | F58: 0.08 | G58: 0.09 | H58: 0.1
A59: 0.02 | B59: 431829 | C59: 265539 | D59: 48344 | E59: -234400 | F59: -601382 | G59: -1076403 | H59: -1689719
A60: 0.03 | B60: 658494 | C60: 488042 | D60: 266061 | E60: -22200 | F60: -395557 | G60: -877961 | H60: -1499847
A61: 0.04 | B61: 932449 | C61: 757267 | D61: 529870 | E61: 235389 | F61: -145128 | G61: -635795 | H61: -1267235
A62: 0.05 | B62: 1300864 | C62: 1120293 | D62: 886748 | E62: 585235 | F62: 196652 | G62: -303284 | H62: -945406
A63: 0.06 | B63: 1793682 | C63: 1606955 | D63: 1366413 | E63: 1056926 | F63: 659235 | G63: 148867 | H63: -505230

Sheet Inputs
A1: Rent vs Buy Model: Inputs
A2: Edit the blue cells (yellow = the assumptions that move the answer most). Everything else is a formula. Example row values below are the national defaults as of Oct 2, 2026.
A3: Input | B3: Value | C3: Unit | D3: Source / Note | E3: Your Value (Used When Preset = Custom (Use My Inputs))
A4: Market | B4: Custom (Use My Inputs) | D4: One of 18 metros with fully sourced data: sets price, rent, property tax and cap, rent growth and the price-to-rent gap (see Presets sheet). Custom (Use My Inputs) = use your values in column E.
A5: Home Price Path | B5: Custom (Use My Inputs) | C5: =IF(Inputs!$B$32="Fixed",TEXT(Inputs!$B$20,"0.0%")&"/yr","Reverting") -> 4.0%/yr | D5: Prices Track Rents / Local Historical Trend / Slow, Typical or Fast Reversion (half-life 24, 11 or 2 years). Column C shows the appreciation used. Custom (Use My Inputs) = use column E.
A6: Investment Return | B6: Custom (Use My Inputs) | D6: Conservative: 5% (Vanguard 10-Year Forecast) / Moderate: 7% / Historical: 10% (S&P 500 Since 1928). Custom (Use My Inputs) = use column E.
A7: Home Price | B7: =IF(Inputs!$B$4="Custom (Use My Inputs)",Inputs!$E$7,INDEX(Presets!$B$5:$B$23,MATCH(Inputs!$B$4,Presets!$A$5:$A$23,0))) -> 500000 | C7: $ | D7: Your input (placeholder default). | E7: 500000
A8: Down Payment | B8: 0.2 | C8: % of price | D8: Your input. Below 20% triggers PMI.
A9: Loan Term (15 or 30) | B9: 30 | C9: years | D9: Your choice.
A10: Mortgage Rate | B10: 0.0728 | C10: annual | D10: Freddie Mac PMMS, Oct 1, 2026: 30-yr 7.28%, 15-yr 6.60% (20% down, excellent credit). https://www.globenewswire.com/news-release/2026/10/01/3373202/0/en/mortgage-rates-average-7-28.html
A11: Buyer Closing Costs | B11: 0.025 | C11: % of price | D11: Estimate. LodeStar 2026: title/settlement/recording/transfer taxes avg 1.04% of price, excluding lender fees. https://www.lodestarss.com/?p=17088
A12: Property Tax | B12: =IF(Inputs!$B$4="Custom (Use My Inputs)",Inputs!$E$12,INDEX(Presets!$D$5:$D$23,MATCH(Inputs!$B$4,Presets!$A$5:$A$23,0))) -> 0.009 | C12: % of value/yr | D12: NAHB analysis of 2024 ACS: $8.88 per $1,000 of value nationally. Use your county's rate. https://eyeonhousing.org/2025/11/property-taxes-by-state-2024/ | E12: 0.009
A13: Homeowners Insurance | B13: 0.005 | C13: % of price/yr | D13: Estimate. Applied to purchase price, then grown with inflation (tracks rebuild cost, not land value). NAIC 2022 data: premiums +10.5% that year, wide state variation. Get a quote.
A14: Maintenance and Repairs | B14: 0.01 | C14: % of price/yr | D14: Applied to purchase price, then grown with inflation. Harvard JCHS: ~$472B/yr owner improvement and repair spending vs ~$51.7T owner-occupied value (~1.1%).
A15: HOA Dues | B15: 0 | C15: $/month | D15: Your input. Grows with inflation.
A16: PMI Rate (If Under 20% Down) | B16: 0.005 | C16: % of loan/yr | D16: Urban Institute range 0.46%-1.5% by credit score. Stops at 78% of original value or the loan-term midpoint, whichever is first (Homeowners Protection Act).
A17: Monthly Rent Today (Comparable Home) | B17: =IF(Inputs!$B$4="Custom (Use My Inputs)",Inputs!$E$17,IF(INDEX(Presets!$C$5:$C$23,MATCH(Inputs!$B$4,Presets!$A$5:$A$23,0))="",Inputs!$E$17,INDEX(Presets!$C$5:$C$23,MATCH(Inputs!$B$4,Presets!$A$5:$A$23,0)))) -> 2500 | C17: $/month | D17: Your input (placeholder default). The single most important input. | E17: 2500
A18: Rent Growth | B18: =IF(Inputs!$B$4="Custom (Use My Inputs)",Inputs!$E$18,INDEX(Presets!$G$5:$G$23,MATCH(Inputs!$B$4,Presets!$A$5:$A$23,0))) -> 0.035 | C18: annual | D18: BLS CPI rent of primary residence, 1982-84 to Jan 2026: ~3.55%/yr. https://fred.stlouisfed.org/series/CUUR0000SEHA | E18: 0.035
A19: Renter's Insurance | B19: 15 | C19: $/month | D19: Estimate. Grows with inflation.
A20: Home Appreciation | B20: =IF(Inputs!$B$5="Prices Track Rents",Inputs!$B$18,IF(Inputs!$B$5="Local Historical Trend",IF(Inputs!$B$4="Custom (Use My Inputs)",Inputs!$E$20,INDEX(Presets!$H$5:$H$23,MATCH(Inputs!$B$4,Presets!$A$5:$A$23,0))),Inputs!$E$20)) -> 0.04 | C20: annual | D20: FHFA HPI 1975Q1-2026Q1: 5.0%/yr; 1985-2026: 4.3%; 2006-2026: 3.4%. Damodaran real estate 1928-2025: 4.2%. | E20: 0.04
A21: Investment Return (Renter's Portfolio) | B21: =IF(Inputs!$B$6="Custom (Use My Inputs)",Inputs!$E$21,INDEX(Presets!$B$43:$B$46,MATCH(Inputs!$B$6,Presets!$A$43:$A$46,0))) -> 0.07 | C21: annual | D21: Judgment call: S&P 500 1928-2025 compounded 10.0% (NYU Stern, Damodaran); Vanguard Dec 2025 forecasts ~4-5% for US stocks over 5-10 yrs. | E21: 0.07
A22: Inflation | B22: 0.028 | C22: annual | D22: BLS CPI-U 1982-84 to Jan 2026: ~2.81%/yr. https://fred.stlouisfed.org/series/cpiaucns
A23: Selling Costs | B23: 0.06 | C23: % of sale price | D23: Federal Reserve FEDS Note (May 2025): buyer-agent commission ~2.7% (data through 2023); authors think the seller side likely matches. Lower in the Northeast and California. Plus seller closing costs.
A24: Filing Status (Single or Joint) | B24: Joint | D24: Defaults to Joint; change to Single if you file alone. Sets standard deduction ($16,100 / $32,200 in 2026, IRS) and home sale exclusion ($250k / $500k, IRS Topic 701). Moves the result by six figures.
A25: Itemize When It Beats Standard Deduction (Yes/No) | B25: No | D25: Defaults to No: no mortgage interest deduction is modeled. Yes = take whichever is larger each year, itemizing (mortgage interest + property tax) or the standard deduction.
A26: Federal Marginal Tax Rate | B26: 0.24 | D26: IRS 2026 brackets: 24% applies above $105,700 single / $211,400 joint taxable income.
A27: State and Local Income Tax You Pay | B27: 0 | C27: $/yr | D27: Counts toward SALT cap ($40,400 in 2026, +1%/yr through 2029, $10,000 from 2030; Journal of Accountancy).
A28: Other Itemized Deductions (Charity Etc.) | B28: 0 | C28: $/yr | D28: Your input.
A29: Capital Gains Tax Rate | B29: 0.15 | D29: 2026 long-term rates 0/15/20% (IRS Rev. Proc. 2025-32). Applied to investment gains and home gain above the exclusion.
A30: Years Until You Sell (1-50) | B30: 30 | C30: years | D30: Your input.
A31: Dividend Yield, Taxed Yearly | B31: 0.011 | C31: annual | D31: Part of the investment return, not added to it. Taxed yearly at the capital gains rate; after-tax dividends reinvested and added to basis. S&P 500 ~1.06% (Sep 2026, Multpl from S&P data). Set 0 for 401(k)/IRA money.
A32: Home Price Path (Fixed or Revert) | B32: =IF(Inputs!$B$5="Custom (Use My Inputs)",Inputs!$E$32,INDEX(Presets!$B$33:$B$38,MATCH(Inputs!$B$5,Presets!$A$33:$A$38,0))) -> Fixed | D32: Fixed = grow at the appreciation input (B17). Revert = price-to-rent gap closes by half every half-life (below); prices grow with rents times the change in the ratio. | E32: Fixed
A33: Price-to-Rent vs Long-Run Norm (Revert Mode) | B33: =IF(Inputs!$B$4="Custom (Use My Inputs)",Inputs!$E$33,INDEX(Presets!$F$5:$F$23,MATCH(Inputs!$B$4,Presets!$A$5:$A$23,0))) -> 0.294 | C33: above norm | D33: San Diego 29.4% above its 1990-2019 average (log basis): FHFA San Diego HPI (ATNHPIUS41740Q) / BLS rent CPI, 2025. See the Market presets sheet for other metros. Negative = below norm. | E33: 0.294
A34: Half-Life of the Gap (Revert Mode) | B34: =IF(Inputs!$B$5="Custom (Use My Inputs)",Inputs!$E$34,IF(INDEX(Presets!$C$33:$C$38,MATCH(Inputs!$B$5,Presets!$A$33:$A$38,0))="",Inputs!$E$34,INDEX(Presets!$C$33:$C$38,MATCH(Inputs!$B$5,Presets!$A$33:$A$38,0)))) -> 11 | C34: years | D34: Years for the price-to-rent gap to close by half. Estimated from FHFA/BLS histories of 18 metros: ~11 yrs (1990-2019 data), ~24 yrs (1990-2025); 2000s bust pace ~2 yrs. | E34: 11
A35: Cap on Taxable Value Growth (Blank = None) | B35: =IF(Inputs!$B$4="Custom (Use My Inputs)",IF(Inputs!$E$35="","",Inputs!$E$35),IF(INDEX(Presets!$E$5:$E$23,MATCH(Inputs!$B$4,Presets!$A$5:$A$23,0))="","",INDEX(Presets!$E$5:$E$23,MATCH(Inputs!$B$4,Presets!$A$5:$A$23,0)))) | C35: per year | D35: California Prop 13: 2% (assessed value = purchase price, grows <= 2%/yr, never above market). Blank where homes are reassessed at market value (e.g., Virginia). Sources: San Diego County Treasurer; county assessors.
A37: Derived Values (Formulas)
A38: Down Payment ($) | B38: =Inputs!$B$7*Inputs!$B$8 -> 100000
A39: Loan Amount | B39: =Inputs!$B$7-B38 -> 400000
A40: Closing Costs ($) | B40: =Inputs!$B$7*Inputs!$B$11 -> 12500
A41: Monthly Principal and Interest | B41: =PMT(Inputs!$B$10/12,Inputs!$B$9*12,-B39) -> 2736.8491 | D41: Standard amortization payment.
A42: Monthly Investment Return | B42: =(1+Inputs!$B$21)^(1/12)-1 -> 0.0056541454 | D42: Monthly equivalent of the annual return.
A43: PMI Applies (1 = Yes) | B43: =IF(Inputs!$B$8<0.2,1,0) -> 0
A44: Standard Deduction, 2026 | B44: =IF(Inputs!$B$24="Joint",32200,16100) -> 32200 | D44: IRS 2026 inflation adjustments (One Big Beautiful Bill).
A45: Home Sale Gain Exclusion | B45: =IF(Inputs!$B$24="Joint",500000,250000) -> 500000 | D45: IRS Topic 701 (2 of 5 years as main home).
A46: Mortgage Interest Debt Limit | B46: 750000 | D46: $750,000 acquisition debt, made permanent by OBBBA.
A47: Filing Status Set (1 = Yes) | B47: =IF(OR(Inputs!$B$24="Single",Inputs!$B$24="Joint"),1,0) -> 1 | D47: Results on Summary stay hidden until this is 1.
A48: Monthly Dividend Yield | B48: =Inputs!$B$31/12 -> 0.00091666667
A50: SALT Cap by Calendar Year
A51: 2026 | B51: 40400 | D51: Journal of Accountancy: $40,000 (2025), $40,400 (2026), +1%/yr through 2029, reverts to $10,000 in 2030. Phase-down above $505k MAGI not modeled.
A52: 2027 | B52: 40804
A53: 2028 | B53: 41212
A54: 2029 | B54: 41624
A55: 2030 and Later | B55: 10000

Sheet Monthly
A1: Month | B1: Year | C1: Begin Balance | D1: Interest | E1: Principal | F1: End Balance | G1: PMI | H1: Home Value (Start of yr) | I1: Property Tax | J1: Insurance | K1: Maintenance | L1: HOA | M1: Tax Savings | N1: Owner Cash Cost | O1: Rent Cash Cost | P1: Owner Minus Rent | Q1: Renter Portfolio | R1: Renter Cost Basis | S1: Owner Portfolio | T1: Owner Cost Basis | U1: Renter Dividend Tax | V1: Owner Dividend Tax
A2: 1 | B2: =ROUNDUP(A2/12,0) -> 1 | C2: =Inputs!$B$39 -> 400000 | D2: =IF(AND(A2<=Inputs!$B$9*12,C2>0.000001),C2*Inputs!$B$10/12,0) -> 2426.6667 | E2: =IF(AND(A2<=Inputs!$B$9*12,C2>0.000001),MIN(C2,Inputs!$B$41-D2),0) -> 310.18246 | F2: =C2-E2 -> 399689.82 | G2: =IF(AND(Inputs!$B$43=1,C2>0.78*Inputs!$B$7,A2<=Inputs!$B$9*6),Inputs!$B$16*Inputs!$B$39/12,0) -> 0 | H2: =IF(B2=1,Inputs!$B$7,INDEX(Annual!$AC$2:$AC$51,B2-1)) -> 500000 | I2: =Inputs!$B$12*IF(Inputs!$B$35="",H2,MIN(H2,Inputs!$B$7*(1+Inputs!$B$35)^(B2-1)))/12 -> 375 | J2: =Inputs!$B$13*Inputs!$B$7*(1+Inputs!$B$22)^(B2-1)/12 -> 208.33333 | K2: =Inputs!$B$14*Inputs!$B$7*(1+Inputs!$B$22)^(B2-1)/12 -> 416.66667 | L2: =Inputs!$B$15*(1+Inputs!$B$22)^(B2-1) -> 0 | M2: =INDEX(Annual!$N$2:$N$51,B2)/12 -> 0 | N2: =D2+E2+G2+I2+J2+K2+L2-M2 -> 3736.8491 | O2: =Inputs!$B$17*(1+Inputs!$B$18)^(B2-1)+Inputs!$B$19*(1+Inputs!$B$22)^(B2-1) -> 2515 | P2: =N2-O2 -> 1221.8491 | Q2: =(Inputs!$B$38+Inputs!$B$40)*(1+Inputs!$B$42)-U2+MAX(P2,0) -> 114342.47 | R2: =(Inputs!$B$38+Inputs!$B$40)+(Inputs!$B$38+Inputs!$B$40)*Inputs!$B$48-U2+MAX(P2,0) -> 113809.51 | S2: =0*(1+Inputs!$B$42)-V2+MAX(-P2,0) -> 0 | T2: =0+0*Inputs!$B$48-V2+MAX(-P2,0) -> 0 | U2: =(Inputs!$B$38+Inputs!$B$40)*Inputs!$B$48*Inputs!$B$29 -> 15.46875 | V2: =0*Inputs!$B$48*Inputs!$B$29 -> 0
A3: 2 | B3: =ROUNDUP(A3/12,0) -> 1 | C3: =F2 -> 399689.82 | D3: =IF(AND(A3<=Inputs!$B$9*12,C3>0.000001),C3*Inputs!$B$10/12,0) -> 2424.7849 | E3: =IF(AND(A3<=Inputs!$B$9*12,C3>0.000001),MIN(C3,Inputs!$B$41-D3),0) -> 312.06424 | F3: =C3-E3 -> 399377.75 | G3: =IF(AND(Inputs!$B$43=1,C3>0.78*Inputs!$B$7,A3<=Inputs!$B$9*6),Inputs!$B$16*Inputs!$B$39/12,0) -> 0 | H3: =IF(B3=1,Inputs!$B$7,INDEX(Annual!$AC$2:$AC$51,B3-1)) -> 500000 | I3: =Inputs!$B$12*IF(Inputs!$B$35="",H3,MIN(H3,Inputs!$B$7*(1+Inputs!$B$35)^(B3-1)))/12 -> 375 | J3: =Inputs!$B$13*Inputs!$B$7*(1+Inputs!$B$22)^(B3-1)/12 -> 208.33333 | K3: =Inputs!$B$14*Inputs!$B$7*(1+Inputs!$B$22)^(B3-1)/12 -> 416.66667 | L3: =Inputs!$B$15*(1+Inputs!$B$22)^(B3-1) -> 0 | M3: =INDEX(Annual!$N$2:$N$51,B3)/12 -> 0 | N3: =D3+E3+G3+I3+J3+K3+L3-M3 -> 3736.8491 | O3: =Inputs!$B$17*(1+Inputs!$B$18)^(B3-1)+Inputs!$B$19*(1+Inputs!$B$22)^(B3-1) -> 2515 | P3: =N3-O3 -> 1221.8491 | Q3: =Q2*(1+Inputs!$B$42)-U3+MAX(P3,0) -> 116195.11 | R3: =R2+Q2*Inputs!$B$48-U3+MAX(P3,0) -> 115120.45 | S3: =S2*(1+Inputs!$B$42)-V3+MAX(-P3,0) -> 0 | T3: =T2+S2*Inputs!$B$48-V3+MAX(-P3,0) -> 0 | U3: =Q2*Inputs!$B$48*Inputs!$B$29 -> 15.72209 | V3: =S2*Inputs!$B$48*Inputs!$B$29 -> 0
A4: 3 | B4: =ROUNDUP(A4/12,0) -> 1 | C4: =F3 -> 399377.75 | D4: =IF(AND(A4<=Inputs!$B$9*12,C4>0.000001),C4*Inputs!$B$10/12,0) -> 2422.8917 | E4: =IF(AND(A4<=Inputs!$B$9*12,C4>0.000001),MIN(C4,Inputs!$B$41-D4),0) -> 313.95743 | F4: =C4-E4 -> 399063.8 | G4: =IF(AND(Inputs!$B$43=1,C4>0.78*Inputs!$B$7,A4<=Inputs!$B$9*6),Inputs!$B$16*Inputs!$B$39/12,0) -> 0 | H4: =IF(B4=1,Inputs!$B$7,INDEX(Annual!$AC$2:$AC$51,B4-1)) -> 500000 | I4: =Inputs!$B$12*IF(Inputs!$B$35="",H4,MIN(H4,Inputs!$B$7*(1+Inputs!$B$35)^(B4-1)))/12 -> 375 | J4: =Inputs!$B$13*Inputs!$B$7*(1+Inputs!$B$22)^(B4-1)/12 -> 208.33333 | K4: =Inputs!$B$14*Inputs!$B$7*(1+Inputs!$B$22)^(B4-1)/12 -> 416.66667 | L4: =Inputs!$B$15*(1+Inputs!$B$22)^(B4-1) -> 0 | M4: =INDEX(Annual!$N$2:$N$51,B4)/12 -> 0 | N4: =D4+E4+G4+I4+J4+K4+L4-M4 -> 3736.8491 | O4: =Inputs!$B$17*(1+Inputs!$B$18)^(B4-1)+Inputs!$B$19*(1+Inputs!$B$22)^(B4-1) -> 2515 | P4: =N4-O4 -> 1221.8491 | Q4: =Q3*(1+Inputs!$B$42)-U4+MAX(P4,0) -> 118057.96 | R4: =R3+Q3*Inputs!$B$48-U4+MAX(P4,0) -> 116432.83 | S4: =S3*(1+Inputs!$B$42)-V4+MAX(-P4,0) -> 0 | T4: =T3+S3*Inputs!$B$48-V4+MAX(-P4,0) -> 0 | U4: =Q3*Inputs!$B$48*Inputs!$B$29 -> 15.976827 | V4: =S3*Inputs!$B$48*Inputs!$B$29 -> 0
A5: 4 | B5: =ROUNDUP(A5/12,0) -> 1 | C5: =F4 -> 399063.8 | D5: =IF(AND(A5<=Inputs!$B$9*12,C5>0.000001),C5*Inputs!$B$10/12,0) -> 2420.987 | E5: =IF(AND(A5<=Inputs!$B$9*12,C5>0.000001),MIN(C5,Inputs!$B$41-D5),0) -> 315.8621 | F5: =C5-E5 -> 398747.93 | G5: =IF(AND(Inputs!$B$43=1,C5>0.78*Inputs!$B$7,A5<=Inputs!$B$9*6),Inputs!$B$16*Inputs!$B$39/12,0) -> 0 | H5: =IF(B5=1,Inputs!$B$7,INDEX(Annual!$AC$2:$AC$51,B5-1)) -> 500000 | I5: =Inputs!$B$12*IF(Inputs!$B$35="",H5,MIN(H5,Inputs!$B$7*(1+Inputs!$B$35)^(B5-1)))/12 -> 375 | J5: =Inputs!$B$13*Inputs!$B$7*(1+Inputs!$B$22)^(B5-1)/12 -> 208.33333 | K5: =Inputs!$B$14*Inputs!$B$7*(1+Inputs!$B$22)^(B5-1)/12 -> 416.66667 | L5: =Inputs!$B$15*(1+Inputs!$B$22)^(B5-1) -> 0 | M5: =INDEX(Annual!$N$2:$N$51,B5)/12 -> 0 | N5: =D5+E5+G5+I5+J5+K5+L5-M5 -> 3736.8491 | O5: =Inputs!$B$17*(1+Inputs!$B$18)^(B5-1)+Inputs!$B$19*(1+Inputs!$B$22)^(B5-1) -> 2515 | P5: =N5-O5 -> 1221.8491 | Q5: =Q4*(1+Inputs!$B$42)-U5+MAX(P5,0) -> 119931.1 | R5: =R4+Q4*Inputs!$B$48-U5+MAX(P5,0) -> 117746.67 | S5: =S4*(1+Inputs!$B$42)-V5+MAX(-P5,0) -> 0 | T5: =T4+S4*Inputs!$B$48-V5+MAX(-P5,0) -> 0 | U5: =Q4*Inputs!$B$48*Inputs!$B$29 -> 16.23297 | V5: =S4*Inputs!$B$48*Inputs!$B$29 -> 0
A6: 5 | B6: =ROUNDUP(A6/12,0) -> 1 | C6: =F5 -> 398747.93 | D6: =IF(AND(A6<=Inputs!$B$9*12,C6>0.000001),C6*Inputs!$B$10/12,0) -> 2419.0708 | E6: =IF(AND(A6<=Inputs!$B$9*12,C6>0.000001),MIN(C6,Inputs!$B$41-D6),0) -> 317.77833 | F6: =C6-E6 -> 398430.16 | G6: =IF(AND(Inputs!$B$43=1,C6>0.78*Inputs!$B$7,A6<=Inputs!$B$9*6),Inputs!$B$16*Inputs!$B$39/12,0) -> 0 | H6: =IF(B6=1,Inputs!$B$7,INDEX(Annual!$AC$2:$AC$51,B6-1)) -> 500000 | I6: =Inputs!$B$12*IF(Inputs!$B$35="",H6,MIN(H6,Inputs!$B$7*(1+Inputs!$B$35)^(B6-1)))/12 -> 375 | J6: =Inputs!$B$13*Inputs!$B$7*(1+Inputs!$B$22)^(B6-1)/12 -> 208.33333 | K6: =Inputs!$B$14*Inputs!$B$7*(1+Inputs!$B$22)^(B6-1)/12 -> 416.66667 | L6: =Inputs!$B$15*(1+Inputs!$B$22)^(B6-1) -> 0 | M6: =INDEX(Annual!$N$2:$N$51,B6)/12 -> 0 | N6: =D6+E6+G6+I6+J6+K6+L6-M6 -> 3736.8491 | O6: =Inputs!$B$17*(1+Inputs!$B$18)^(B6-1)+Inputs!$B$19*(1+Inputs!$B$22)^(B6-1) -> 2515 | P6: =N6-O6 -> 1221.8491 | Q6: =Q5*(1+Inputs!$B$42)-U6+MAX(P6,0) -> 121814.56 | R6: =R5+Q5*Inputs!$B$48-U6+MAX(P6,0) -> 119061.96 | S6: =S5*(1+Inputs!$B$42)-V6+MAX(-P6,0) -> 0 | T6: =T5+S5*Inputs!$B$48-V6+MAX(-P6,0) -> 0 | U6: =Q5*Inputs!$B$48*Inputs!$B$29 -> 16.490526 | V6: =S5*Inputs!$B$48*Inputs!$B$29 -> 0
A7: 6 | B7: =ROUNDUP(A7/12,0) -> 1 | C7: =F6 -> 398430.16 | D7: =IF(AND(A7<=Inputs!$B$9*12,C7>0.000001),C7*Inputs!$B$10/12,0) -> 2417.1429 | E7: =IF(AND(A7<=Inputs!$B$9*12,C7>0.000001),MIN(C7,Inputs!$B$41-D7),0) -> 319.70619 | F7: =C7-E7 -> 398110.45 | G7: =IF(AND(Inputs!$B$43=1,C7>0.78*Inputs!$B$7,A7<=Inputs!$B$9*6),Inputs!$B$16*Inputs!$B$39/12,0) -> 0 | H7: =IF(B7=1,Inputs!$B$7,INDEX(Annual!$AC$2:$AC$51,B7-1)) -> 500000 | I7: =Inputs!$B$12*IF(Inputs!$B$35="",H7,MIN(H7,Inputs!$B$7*(1+Inputs!$B$35)^(B7-1)))/12 -> 375 | J7: =Inputs!$B$13*Inputs!$B$7*(1+Inputs!$B$22)^(B7-1)/12 -> 208.33333 | K7: =Inputs!$B$14*Inputs!$B$7*(1+Inputs!$B$22)^(B7-1)/12 -> 416.66667 | L7: =Inputs!$B$15*(1+Inputs!$B$22)^(B7-1) -> 0 | M7: =INDEX(Annual!$N$2:$N$51,B7)/12 -> 0 | N7: =D7+E7+G7+I7+J7+K7+L7-M7 -> 3736.8491 | O7: =Inputs!$B$17*(1+Inputs!$B$18)^(B7-1)+Inputs!$B$19*(1+Inputs!$B$22)^(B7-1) -> 2515 | P7: =N7-O7 -> 1221.8491 | Q7: =Q6*(1+Inputs!$B$42)-U7+MAX(P7,0) -> 123708.42 | R7: =R6+Q6*Inputs!$B$48-U7+MAX(P7,0) -> 120378.73 | S7: =S6*(1+Inputs!$B$42)-V7+MAX(-P7,0) -> 0 | T7: =T6+S6*Inputs!$B$48-V7+MAX(-P7,0) -> 0 | U7: =Q6*Inputs!$B$48*Inputs!$B$29 -> 16.749502 | V7: =S6*Inputs!$B$48*Inputs!$B$29 -> 0
A8: 7 | B8: =ROUNDUP(A8/12,0) -> 1 | C8: =F7 -> 398110.45 | D8: =IF(AND(A8<=Inputs!$B$9*12,C8>0.000001),C8*Inputs!$B$10/12,0) -> 2415.2034 | E8: =IF(AND(A8<=Inputs!$B$9*12,C8>0.000001),MIN(C8,Inputs!$B$41-D8),0) -> 321.64574 | F8: =C8-E8 -> 397788.8 | G8: =IF(AND(Inputs!$B$43=1,C8>0.78*Inputs!$B$7,A8<=Inputs!$B$9*6),Inputs!$B$16*Inputs!$B$39/12,0) -> 0 | H8: =IF(B8=1,Inputs!$B$7,INDEX(Annual!$AC$2:$AC$51,B8-1)) -> 500000 | I8: =Inputs!$B$12*IF(Inputs!$B$35="",H8,MIN(H8,Inputs!$B$7*(1+Inputs!$B$35)^(B8-1)))/12 -> 375 | J8: =Inputs!$B$13*Inputs!$B$7*(1+Inputs!$B$22)^(B8-1)/12 -> 208.33333 | K8: =Inputs!$B$14*Inputs!$B$7*(1+Inputs!$B$22)^(B8-1)/12 -> 416.66667 | L8: =Inputs!$B$15*(1+Inputs!$B$22)^(B8-1) -> 0 | M8: =INDEX(Annual!$N$2:$N$51,B8)/12 -> 0 | N8: =D8+E8+G8+I8+J8+K8+L8-M8 -> 3736.8491 | O8: =Inputs!$B$17*(1+Inputs!$B$18)^(B8-1)+Inputs!$B$19*(1+Inputs!$B$22)^(B8-1) -> 2515 | P8: =N8-O8 -> 1221.8491 | Q8: =Q7*(1+Inputs!$B$42)-U8+MAX(P8,0) -> 125612.73 | R8: =R7+Q7*Inputs!$B$48-U8+MAX(P8,0) -> 121696.96 | S8: =S7*(1+Inputs!$B$42)-V8+MAX(-P8,0) -> 0 | T8: =T7+S7*Inputs!$B$48-V8+MAX(-P8,0) -> 0 | U8: =Q7*Inputs!$B$48*Inputs!$B$29 -> 17.009908 | V8: =S7*Inputs!$B$48*Inputs!$B$29 -> 0
A9: 8 | B9: =ROUNDUP(A9/12,0) -> 1 | C9: =F8 -> 397788.8 | D9: =IF(AND(A9<=Inputs!$B$9*12,C9>0.000001),C9*Inputs!$B$10/12,0) -> 2413.2521 | E9: =IF(AND(A9<=Inputs!$B$9*12,C9>0.000001),MIN(C9,Inputs!$B$41-D9),0) -> 323.59705 | F9: =C9-E9 -> 397465.21 | G9: =IF(AND(Inputs!$B$43=1,C9>0.78*Inputs!$B$7,A9<=Inputs!$B$9*6),Inputs!$B$16*Inputs!$B$39/12,0) -> 0 | H9: =IF(B9=1,Inputs!$B$7,INDEX(Annual!$AC$2:$AC$51,B9-1)) -> 500000 | I9: =Inputs!$B$12*IF(Inputs!$B$35="",H9,MIN(H9,Inputs!$B$7*(1+Inputs!$B$35)^(B9-1)))/12 -> 375 | J9: =Inputs!$B$13*Inputs!$B$7*(1+Inputs!$B$22)^(B9-1)/12 -> 208.33333 | K9: =Inputs!$B$14*Inputs!$B$7*(1+Inputs!$B$22)^(B9-1)/12 -> 416.66667 | L9: =Inputs!$B$15*(1+Inputs!$B$22)^(B9-1) -> 0 | M9: =INDEX(Annual!$N$2:$N$51,B9)/12 -> 0 | N9: =D9+E9+G9+I9+J9+K9+L9-M9 -> 3736.8491 | O9: =Inputs!$B$17*(1+Inputs!$B$18)^(B9-1)+Inputs!$B$19*(1+Inputs!$B$22)^(B9-1) -> 2515 | P9: =N9-O9 -> 1221.8491 | Q9: =Q8*(1+Inputs!$B$42)-U9+MAX(P9,0) -> 127527.54 | R9: =R8+Q8*Inputs!$B$48-U9+MAX(P9,0) -> 123016.69 | S9: =S8*(1+Inputs!$B$42)-V9+MAX(-P9,0) -> 0 | T9: =T8+S8*Inputs!$B$48-V9+MAX(-P9,0) -> 0 | U9: =Q8*Inputs!$B$48*Inputs!$B$29 -> 17.27175 | V9: =S8*Inputs!$B$48*Inputs!$B$29 -> 0
A10: 9 | B10: =ROUNDUP(A10/12,0) -> 1 | C10: =F9 -> 397465.21 | D10: =IF(AND(A10<=Inputs!$B$9*12,C10>0.000001),C10*Inputs!$B$10/12,0) -> 2411.2889 | E10: =IF(AND(A10<=Inputs!$B$9*12,C10>0.000001),MIN(C10,Inputs!$B$41-D10),0) -> 325.56021 | F10: =C10-E10 -> 397139.65 | G10: =IF(AND(Inputs!$B$43=1,C10>0.78*Inputs!$B$7,A10<=Inputs!$B$9*6),Inputs!$B$16*Inputs!$B$39/12,0) -> 0 | H10: =IF(B10=1,Inputs!$B$7,INDEX(Annual!$AC$2:$AC$51,B10-1)) -> 500000 | I10: =Inputs!$B$12*IF(Inputs!$B$35="",H10,MIN(H10,Inputs!$B$7*(1+Inputs!$B$35)^(B10-1)))/12 -> 375 | J10: =Inputs!$B$13*Inputs!$B$7*(1+Inputs!$B$22)^(B10-1)/12 -> 208.33333 | K10: =Inputs!$B$14*Inputs!$B$7*(1+Inputs!$B$22)^(B10-1)/12 -> 416.66667 | L10: =Inputs!$B$15*(1+Inputs!$B$22)^(B10-1) -> 0 | M10: =INDEX(Annual!$N$2:$N$51,B10)/12 -> 0 | N10: =D10+E10+G10+I10+J10+K10+L10-M10 -> 3736.8491 | O10: =Inputs!$B$17*(1+Inputs!$B$18)^(B10-1)+Inputs!$B$19*(1+Inputs!$B$22)^(B10-1) -> 2515 | P10: =N10-O10 -> 1221.8491 | Q10: =Q9*(1+Inputs!$B$42)-U10+MAX(P10,0) -> 129452.91 | R10: =R9+Q9*Inputs!$B$48-U10+MAX(P10,0) -> 124337.9 | S10: =S9*(1+Inputs!$B$42)-V10+MAX(-P10,0) -> 0 | T10: =T9+S9*Inputs!$B$48-V10+MAX(-P10,0) -> 0 | U10: =Q9*Inputs!$B$48*Inputs!$B$29 -> 17.535036 | V10: =S9*Inputs!$B$48*Inputs!$B$29 -> 0
A11: 10 | B11: =ROUNDUP(A11/12,0) -> 1 | C11: =F10 -> 397139.65 | D11: =IF(AND(A11<=Inputs!$B$9*12,C11>0.000001),C11*Inputs!$B$10/12,0) -> 2409.3139 | E11: =IF(AND(A11<=Inputs!$B$9*12,C11>0.000001),MIN(C11,Inputs!$B$41-D11),0) -> 327.53528 | F11: =C11-E11 -> 396812.11 | G11: =IF(AND(Inputs!$B$43=1,C11>0.78*Inputs!$B$7,A11<=Inputs!$B$9*6),Inputs!$B$16*Inputs!$B$39/12,0) -> 0 | H11: =IF(B11=1,Inputs!$B$7,INDEX(Annual!$AC$2:$AC$51,B11-1)) -> 500000 | I11: =Inputs!$B$12*IF(Inputs!$B$35="",H11,MIN(H11,Inputs!$B$7*(1+Inputs!$B$35)^(B11-1)))/12 -> 375 | J11: =Inputs!$B$13*Inputs!$B$7*(1+Inputs!$B$22)^(B11-1)/12 -> 208.33333 | K11: =Inputs!$B$14*Inputs!$B$7*(1+Inputs!$B$22)^(B11-1)/12 -> 416.66667 | L11: =Inputs!$B$15*(1+Inputs!$B$22)^(B11-1) -> 0 | M11: =INDEX(Annual!$N$2:$N$51,B11)/12 -> 0 | N11: =D11+E11+G11+I11+J11+K11+L11-M11 -> 3736.8491 | O11: =Inputs!$B$17*(1+Inputs!$B$18)^(B11-1)+Inputs!$B$19*(1+Inputs!$B$22)^(B11-1) -> 2515 | P11: =N11-O11 -> 1221.8491 | Q11: =Q10*(1+Inputs!$B$42)-U11+MAX(P11,0) -> 131388.9 | R11: =R10+Q10*Inputs!$B$48-U11+MAX(P11,0) -> 125660.62 | S11: =S10*(1+Inputs!$B$42)-V11+MAX(-P11,0) -> 0 | T11: =T10+S10*Inputs!$B$48-V11+MAX(-P11,0) -> 0 | U11: =Q10*Inputs!$B$48*Inputs!$B$29 -> 17.799775 | V11: =S10*Inputs!$B$48*Inputs!$B$29 -> 0
A12: 11 | B12: =ROUNDUP(A12/12,0) -> 1 | C12: =F11 -> 396812.11 | D12: =IF(AND(A12<=Inputs!$B$9*12,C12>0.000001),C12*Inputs!$B$10/12,0) -> 2407.3268 | E12: =IF(AND(A12<=Inputs!$B$9*12,C12>0.000001),MIN(C12,Inputs!$B$41-D12),0) -> 329.52232 | F12: =C12-E12 -> 396482.59 | G12: =IF(AND(Inputs!$B$43=1,C12>0.78*Inputs!$B$7,A12<=Inputs!$B$9*6),Inputs!$B$16*Inputs!$B$39/12,0) -> 0 | H12: =IF(B12=1,Inputs!$B$7,INDEX(Annual!$AC$2:$AC$51,B12-1)) -> 500000 | I12: =Inputs!$B$12*IF(Inputs!$B$35="",H12,MIN(H12,Inputs!$B$7*(1+Inputs!$B$35)^(B12-1)))/12 -> 375 | J12: =Inputs!$B$13*Inputs!$B$7*(1+Inputs!$B$22)^(B12-1)/12 -> 208.33333 | K12: =Inputs!$B$14*Inputs!$B$7*(1+Inputs!$B$22)^(B12-1)/12 -> 416.66667 | L12: =Inputs!$B$15*(1+Inputs!$B$22)^(B12-1) -> 0 | M12: =INDEX(Annual!$N$2:$N$51,B12)/12 -> 0 | N12: =D12+E12+G12+I12+J12+K12+L12-M12 -> 3736.8491 | O12: =Inputs!$B$17*(1+Inputs!$B$18)^(B12-1)+Inputs!$B$19*(1+Inputs!$B$22)^(B12-1) -> 2515 | P12: =N12-O12 -> 1221.8491 | Q12: =Q11*(1+Inputs!$B$42)-U12+MAX(P12,0) -> 133335.58 | R12: =R11+Q11*Inputs!$B$48-U12+MAX(P12,0) -> 126984.84 | S12: =S11*(1+Inputs!$B$42)-V12+MAX(-P12,0) -> 0 | T12: =T11+S11*Inputs!$B$48-V12+MAX(-P12,0) -> 0 | U12: =Q11*Inputs!$B$48*Inputs!$B$29 -> 18.065974 | V12: =S11*Inputs!$B$48*Inputs!$B$29 -> 0
A13: 12 | B13: =ROUNDUP(A13/12,0) -> 1 | C13: =F12 -> 396482.59 | D13: =IF(AND(A13<=Inputs!$B$9*12,C13>0.000001),C13*Inputs!$B$10/12,0) -> 2405.3277 | E13: =IF(AND(A13<=Inputs!$B$9*12,C13>0.000001),MIN(C13,Inputs!$B$41-D13),0) -> 331.52142 | F13: =C13-E13 -> 396151.07 | G13: =IF(AND(Inputs!$B$43=1,C13>0.78*Inputs!$B$7,A13<=Inputs!$B$9*6),Inputs!$B$16*Inputs!$B$39/12,0) -> 0 | H13: =IF(B13=1,Inputs!$B$7,INDEX(Annual!$AC$2:$AC$51,B13-1)) -> 500000 | I13: =Inputs!$B$12*IF(Inputs!$B$35="",H13,MIN(H13,Inputs!$B$7*(1+Inputs!$B$35)^(B13-1)))/12 -> 375 | J13: =Inputs!$B$13*Inputs!$B$7*(1+Inputs!$B$22)^(B13-1)/12 -> 208.33333 | K13: =Inputs!$B$14*Inputs!$B$7*(1+Inputs!$B$22)^(B13-1)/12 -> 416.66667 | L13: =Inputs!$B$15*(1+Inputs!$B$22)^(B13-1) -> 0 | M13: =INDEX(Annual!$N$2:$N$51,B13)/12 -> 0 | N13: =D13+E13+G13+I13+J13+K13+L13-M13 -> 3736.8491 | O13: =Inputs!$B$17*(1+Inputs!$B$18)^(B13-1)+Inputs!$B$19*(1+Inputs!$B$22)^(B13-1) -> 2515 | P13: =N13-O13 -> 1221.8491 | Q13: =Q12*(1+Inputs!$B$42)-U13+MAX(P13,0) -> 135292.99 | R13: =R12+Q12*Inputs!$B$48-U13+MAX(P13,0) -> 128310.58 | S13: =S12*(1+Inputs!$B$42)-V13+MAX(-P13,0) -> 0 | T13: =T12+S12*Inputs!$B$48-V13+MAX(-P13,0) -> 0 | U13: =Q12*Inputs!$B$48*Inputs!$B$29 -> 18.333642 | V13: =S12*Inputs!$B$48*Inputs!$B$29 -> 0
A14: 13 | B14: =ROUNDUP(A14/12,0) -> 2 | C14: =F13 -> 396151.07 | D14: =IF(AND(A14<=Inputs!$B$9*12,C14>0.000001),C14*Inputs!$B$10/12,0) -> 2403.3165 | E14: =IF(AND(A14<=Inputs!$B$9*12,C14>0.000001),MIN(C14,Inputs!$B$41-D14),0) -> 333.53265 | F14: =C14-E14 -> 395817.53 | G14: =IF(AND(Inputs!$B$43=1,C14>0.78*Inputs!$B$7,A14<=Inputs!$B$9*6),Inputs!$B$16*Inputs!$B$39/12,0) -> 0 | H14: =IF(B14=1,Inputs!$B$7,INDEX(Annual!$AC$2:$AC$51,B14-1)) -> 520000 | I14: =Inputs!$B$12*IF(Inputs!$B$35="",H14,MIN(H14,Inputs!$B$7*(1+Inputs!$B$35)^(B14-1)))/12 -> 390 | J14: =Inputs!$B$13*Inputs!$B$7*(1+Inputs!$B$22)^(B14-1)/12 -> 214.16667 | K14: =Inputs!$B$14*Inputs!$B$7*(1+Inputs!$B$22)^(B14-1)/12 -> 428.33333 | L14: =Inputs!$B$15*(1+Inputs!$B$22)^(B14-1) -> 0 | M14: =INDEX(Annual!$N$2:$N$51,B14)/12 -> 0 | N14: =D14+E14+G14+I14+J14+K14+L14-M14 -> 3769.3491 | O14: =Inputs!$B$17*(1+Inputs!$B$18)^(B14-1)+Inputs!$B$19*(1+Inputs!$B$22)^(B14-1) -> 2602.92 | P14: =N14-O14 -> 1166.4291 | Q14: =Q13*(1+Inputs!$B$42)-U14+MAX(P14,0) -> 137205.79 | R14: =R13+Q13*Inputs!$B$48-U14+MAX(P14,0) -> 129582.42 | S14: =S13*(1+Inputs!$B$42)-V14+MAX(-P14,0) -> 0 | T14: =T13+S13*Inputs!$B$48-V14+MAX(-P14,0) -> 0 | U14: =Q13*Inputs!$B$48*Inputs!$B$29 -> 18.602786 | V14: =S13*Inputs!$B$48*Inputs!$B$29 -> 0
... A601: 600 | B601: =ROUNDUP(A601/12,0) -> 50 | C601: =F600 -> 1.286935e-10 | D601: =IF(AND(A601<=Inputs!$B$9*12,C601>0.000001),C601*Inputs!$B$10/12,0) -> 0 | E601: =IF(AND(A601<=Inputs!$B$9*12,C601>0.000001),MIN(C601,Inputs!$B$41-D601),0) -> 0 | F601: =C601-E601 -> 1.286935e-10 | G601: =IF(AND(Inputs!$B$43=1,C601>0.78*Inputs!$B$7,A601<=Inputs!$B$9*6),Inputs!$B$16*Inputs!$B$39/12,0) -> 0 | H601: =IF(B601=1,Inputs!$B$7,INDEX(Annual!$AC$2:$AC$51,B601-1)) -> 3416674.7 | I601: =Inputs!$B$12*IF(Inputs!$B$35="",H601,MIN(H601,Inputs!$B$7*(1+Inputs!$B$35)^(B601-1)))/12 -> 2562.506 | J601: =Inputs!$B$13*Inputs!$B$7*(1+Inputs!$B$22)^(B601-1)/12 -> 806.16025 | K601: =Inputs!$B$14*Inputs!$B$7*(1+Inputs!$B$22)^(B601-1)/12 -> 1612.3205 | L601: =Inputs!$B$15*(1+Inputs!$B$22)^(B601-1) -> 0 | M601: =INDEX(Annual!$N$2:$N$51,B601)/12 -> 0 | N601: =D601+E601+G601+I601+J601+K601+L601-M601 -> 4980.9868 | O601: =Inputs!$B$17*(1+Inputs!$B$18)^(B601-1)+Inputs!$B$19*(1+Inputs!$B$22)^(B601-1) -> 13548.205 | P601: =N601-O601 -> -8567.2183 | Q601: =Q600*(1+Inputs!$B$42)-U601+MAX(P601,0) -> 5707353.6 | R601: =R600+Q600*Inputs!$B$48-U601+MAX(P601,0) -> 1023312.3 | S601: =S600*(1+Inputs!$B$42)-V601+MAX(-P601,0) -> 3466218.6 | T601: =T600+S600*Inputs!$B$48-V601+MAX(-P601,0) -> 1880407.7 | U601: =Q600*Inputs!$B$48*Inputs!$B$29 -> 780.45563 | V601: =S600*Inputs!$B$48*Inputs!$B$29 -> 472.81869

Sheet Annual
A1: Year | B1: Calendar Year | C1: Interest | D1: Principal | E1: Avg Balance | F1: Deductible Interest | G1: Property Tax | H1: SALT Cap | I1: Standard Deduction | J1: Owner Itemized | K1: Renter Itemized | L1: Owner Itemizes? | N1: Tax Savings | O1: Owner Cash Cost | P1: Rent Cash Cost | Q1: Home Value (End of yr) | R1: Loan Balance | S1: Selling Costs | T1: Tax on Home Gain | U1: Owner Portfolio After Tax | V1: Buy Net Worth | W1: Rent Net Worth | X1: Buy Minus Rent | Y1: Inflation Deflator | Z1: Buy Minus Rent (Today's $) | AA1: Ahead for Good from This Year | AB1: Appreciation This Year | AC1: Home Value (End of yr, Path)
A2: 1 | B2: =TEXT(2026+A2,"0") -> 2027 | C2: =SUMIF(Monthly!$B$2:$B$601,A2,Monthly!$D$2:$D$601) -> 28993.257 | D2: =SUMIF(Monthly!$B$2:$B$601,A2,Monthly!$E$2:$E$601) -> 3848.9328 | E2: =AVERAGEIF(Monthly!$B$2:$B$601,A2,Monthly!$C$2:$C$601) -> 398259.02 | F2: =C2*IF(E2<=Inputs!$B$46,1,Inputs!$B$46/E2) -> 28993.257 | G2: =Inputs!$B$12*IF(Inputs!$B$35="",Inputs!$B$7,MIN(Inputs!$B$7,Inputs!$B$7*(1+Inputs!$B$35)^(A2-1))) -> 4500 | H2: =Inputs!$B$52 -> 40804 | I2: =Inputs!$B$44*(1+Inputs!$B$22)^A2 -> 33101.6 | J2: =F2+MIN(H2,G2+Inputs!$B$27)+Inputs!$B$28 -> 33493.257 | K2: =MIN(H2,Inputs!$B$27)+Inputs!$B$28 -> 0 | L2: =IF(J2>I2,"Yes","No") -> Yes | N2: =IF(Inputs!$B$25="Yes",Inputs!$B$26*(MAX(I2,J2)-MAX(I2,K2)),0) -> 0 | O2: =SUMIF(Monthly!$B$2:$B$601,A2,Monthly!$N$2:$N$601) -> 44842.19 | P2: =SUMIF(Monthly!$B$2:$B$601,A2,Monthly!$O$2:$O$601) -> 30180 | Q2: =AC2 -> 520000 | R2: =INDEX(Monthly!$F$2:$F$601,A2*12) -> 396151.07 | S2: =Q2*Inputs!$B$23 -> 31200 | T2: =MAX(0,Q2-S2-(Inputs!$B$7+Inputs!$B$40)-IF(A2>=2,Inputs!$B$45,0))*Inputs!$B$29 -> 0 | U2: =INDEX(Monthly!$S$2:$S$601,A2*12)-Inputs!$B$29*MAX(0,INDEX(Monthly!$S$2:$S$601,A2*12)-INDEX(Monthly!$T$2:$T$601,A2*12)) -> 0 | V2: =Q2-S2-R2-T2+U2 -> 92648.933 | W2: =INDEX(Monthly!$Q$2:$Q$601,A2*12)-Inputs!$B$29*MAX(0,INDEX(Monthly!$Q$2:$Q$601,A2*12)-INDEX(Monthly!$R$2:$R$601,A2*12)) -> 134245.63 | X2: =V2-W2 -> -41596.698 | Y2: =(1+Inputs!$B$22)^A2 -> 1.028 | Z2: =X2/Y2 -> -40463.714 | AA2: =IF(AND(X2>=0,COUNTIF(X2:X$51,"<0")=0),A2,"") | AB2: =IF(Inputs!$B$32="Revert",(1+Inputs!$B$18)*EXP(LN(1+Inputs!$B$33)*(0.5^(A2/Inputs!$B$34)-0.5^((A2-1)/Inputs!$B$34)))-1,Inputs!$B$20) -> 0.04 | AC2: =Inputs!$B$7*(1+AB2) -> 520000
A3: 2 | B3: =TEXT(2026+A3,"0") -> 2028 | C3: =SUMIF(Monthly!$B$2:$B$601,A3,Monthly!$D$2:$D$601) -> 28703.513 | D3: =SUMIF(Monthly!$B$2:$B$601,A3,Monthly!$E$2:$E$601) -> 4138.6762 | E3: =AVERAGEIF(Monthly!$B$2:$B$601,A3,Monthly!$C$2:$C$601) -> 394279.03 | F3: =C3*IF(E3<=Inputs!$B$46,1,Inputs!$B$46/E3) -> 28703.513 | G3: =Inputs!$B$12*IF(Inputs!$B$35="",AC2,MIN(AC2,Inputs!$B$7*(1+Inputs!$B$35)^(A3-1))) -> 4680 | H3: =Inputs!$B$53 -> 41212 | I3: =Inputs!$B$44*(1+Inputs!$B$22)^A3 -> 34028.445 | J3: =F3+MIN(H3,G3+Inputs!$B$27)+Inputs!$B$28 -> 33383.513 | K3: =MIN(H3,Inputs!$B$27)+Inputs!$B$28 -> 0 | L3: =IF(J3>I3,"Yes","No") -> No | N3: =IF(Inputs!$B$25="Yes",Inputs!$B$26*(MAX(I3,J3)-MAX(I3,K3)),0) -> 0 | O3: =SUMIF(Monthly!$B$2:$B$601,A3,Monthly!$N$2:$N$601) -> 45232.19 | P3: =SUMIF(Monthly!$B$2:$B$601,A3,Monthly!$O$2:$O$601) -> 31235.04 | Q3: =AC3 -> 540800 | R3: =INDEX(Monthly!$F$2:$F$601,A3*12) -> 392012.39 | S3: =Q3*Inputs!$B$23 -> 32448 | T3: =MAX(0,Q3-S3-(Inputs!$B$7+Inputs!$B$40)-IF(A3>=2,Inputs!$B$45,0))*Inputs!$B$29 -> 0 | U3: =INDEX(Monthly!$S$2:$S$601,A3*12)-Inputs!$B$29*MAX(0,INDEX(Monthly!$S$2:$S$601,A3*12)-INDEX(Monthly!$T$2:$T$601,A3*12)) -> 0 | V3: =Q3-S3-R3-T3+U3 -> 116339.61 | W3: =INDEX(Monthly!$Q$2:$Q$601,A3*12)-Inputs!$B$29*MAX(0,INDEX(Monthly!$Q$2:$Q$601,A3*12)-INDEX(Monthly!$R$2:$R$601,A3*12)) -> 156663.47 | X3: =V3-W3 -> -40323.857 | Y3: =(1+Inputs!$B$22)^A3 -> 1.056784 | Z3: =X3/Y3 -> -38157.142 | AA3: =IF(AND(X3>=0,COUNTIF(X3:X$51,"<0")=0),A3,"") | AB3: =IF(Inputs!$B$32="Revert",(1+Inputs!$B$18)*EXP(LN(1+Inputs!$B$33)*(0.5^(A3/Inputs!$B$34)-0.5^((A3-1)/Inputs!$B$34)))-1,Inputs!$B$20) -> 0.04 | AC3: =AC2*(1+AB3) -> 540800
A4: 3 | B4: =TEXT(2026+A4,"0") -> 2029 | C4: =SUMIF(Monthly!$B$2:$B$601,A4,Monthly!$D$2:$D$601) -> 28391.958 | D4: =SUMIF(Monthly!$B$2:$B$601,A4,Monthly!$E$2:$E$601) -> 4450.2311 | E4: =AVERAGEIF(Monthly!$B$2:$B$601,A4,Monthly!$C$2:$C$601) -> 389999.43 | F4: =C4*IF(E4<=Inputs!$B$46,1,Inputs!$B$46/E4) -> 28391.958 | G4: =Inputs!$B$12*IF(Inputs!$B$35="",AC3,MIN(AC3,Inputs!$B$7*(1+Inputs!$B$35)^(A4-1))) -> 4867.2 | H4: =Inputs!$B$54 -> 41624 | I4: =Inputs!$B$44*(1+Inputs!$B$22)^A4 -> 34981.241 | J4: =F4+MIN(H4,G4+Inputs!$B$27)+Inputs!$B$28 -> 33259.158 | K4: =MIN(H4,Inputs!$B$27)+Inputs!$B$28 -> 0 | L4: =IF(J4>I4,"Yes","No") -> No | N4: =IF(Inputs!$B$25="Yes",Inputs!$B$26*(MAX(I4,J4)-MAX(I4,K4)),0) -> 0 | O4: =SUMIF(Monthly!$B$2:$B$601,A4,Monthly!$N$2:$N$601) -> 45635.27 | P4: =SUMIF(Monthly!$B$2:$B$601,A4,Monthly!$O$2:$O$601) -> 32326.971 | Q4: =AC4 -> 562432 | R4: =INDEX(Monthly!$F$2:$F$601,A4*12) -> 387562.16 | S4: =Q4*Inputs!$B$23 -> 33745.92 | T4: =MAX(0,Q4-S4-(Inputs!$B$7+Inputs!$B$40)-IF(A4>=2,Inputs!$B$45,0))*Inputs!$B$29 -> 0 | U4: =INDEX(Monthly!$S$2:$S$601,A4*12)-Inputs!$B$29*MAX(0,INDEX(Monthly!$S$2:$S$601,A4*12)-INDEX(Monthly!$T$2:$T$601,A4*12)) -> 0 | V4: =Q4-S4-R4-T4+U4 -> 141123.92 | W4: =INDEX(Monthly!$Q$2:$Q$601,A4*12)-Inputs!$B$29*MAX(0,INDEX(Monthly!$Q$2:$Q$601,A4*12)-INDEX(Monthly!$R$2:$R$601,A4*12)) -> 179780.78 | X4: =V4-W4 -> -38656.855 | Y4: =(1+Inputs!$B$22)^A4 -> 1.086374 | Z4: =X4/Y4 -> -35583.378 | AA4: =IF(AND(X4>=0,COUNTIF(X4:X$51,"<0")=0),A4,"") | AB4: =IF(Inputs!$B$32="Revert",(1+Inputs!$B$18)*EXP(LN(1+Inputs!$B$33)*(0.5^(A4/Inputs!$B$34)-0.5^((A4-1)/Inputs!$B$34)))-1,Inputs!$B$20) -> 0.04 | AC4: =AC3*(1+AB4) -> 562432
A5: 4 | B5: =TEXT(2026+A5,"0") -> 2030 | C5: =SUMIF(Monthly!$B$2:$B$601,A5,Monthly!$D$2:$D$601) -> 28056.95 | D5: =SUMIF(Monthly!$B$2:$B$601,A5,Monthly!$E$2:$E$601) -> 4785.2396 | E5: =AVERAGEIF(Monthly!$B$2:$B$601,A5,Monthly!$C$2:$C$601) -> 385397.66 | F5: =C5*IF(E5<=Inputs!$B$46,1,Inputs!$B$46/E5) -> 28056.95 | G5: =Inputs!$B$12*IF(Inputs!$B$35="",AC4,MIN(AC4,Inputs!$B$7*(1+Inputs!$B$35)^(A5-1))) -> 5061.888 | H5: =Inputs!$B$55 -> 10000 | I5: =Inputs!$B$44*(1+Inputs!$B$22)^A5 -> 35960.716 | J5: =F5+MIN(H5,G5+Inputs!$B$27)+Inputs!$B$28 -> 33118.838 | K5: =MIN(H5,Inputs!$B$27)+Inputs!$B$28 -> 0 | L5: =IF(J5>I5,"Yes","No") -> No | N5: =IF(Inputs!$B$25="Yes",Inputs!$B$26*(MAX(I5,J5)-MAX(I5,K5)),0) -> 0 | O5: =SUMIF(Monthly!$B$2:$B$601,A5,Monthly!$N$2:$N$601) -> 46051.882 | P5: =SUMIF(Monthly!$B$2:$B$601,A5,Monthly!$O$2:$O$601) -> 33457.084 | Q5: =AC5 -> 584929.28 | R5: =INDEX(Monthly!$F$2:$F$601,A5*12) -> 382776.92 | S5: =Q5*Inputs!$B$23 -> 35095.757 | T5: =MAX(0,Q5-S5-(Inputs!$B$7+Inputs!$B$40)-IF(A5>=2,Inputs!$B$45,0))*Inputs!$B$29 -> 0 | U5: =INDEX(Monthly!$S$2:$S$601,A5*12)-Inputs!$B$29*MAX(0,INDEX(Monthly!$S$2:$S$601,A5*12)-INDEX(Monthly!$T$2:$T$601,A5*12)) -> 0 | V5: =Q5-S5-R5-T5+U5 -> 167056.6 | W5: =INDEX(Monthly!$Q$2:$Q$601,A5*12)-Inputs!$B$29*MAX(0,INDEX(Monthly!$Q$2:$Q$601,A5*12)-INDEX(Monthly!$R$2:$R$601,A5*12)) -> 203626.04 | X5: =V5-W5 -> -36569.435 | Y5: =(1+Inputs!$B$22)^A5 -> 1.1167924 | Z5: =X5/Y5 -> -32745.06 | AA5: =IF(AND(X5>=0,COUNTIF(X5:X$51,"<0")=0),A5,"") | AB5: =IF(Inputs!$B$32="Revert",(1+Inputs!$B$18)*EXP(LN(1+Inputs!$B$33)*(0.5^(A5/Inputs!$B$34)-0.5^((A5-1)/Inputs!$B$34)))-1,Inputs!$B$20) -> 0.04 | AC5: =AC4*(1+AB5) -> 584929.28
A6: 5 | B6: =TEXT(2026+A6,"0") -> 2031 | C6: =SUMIF(Monthly!$B$2:$B$601,A6,Monthly!$D$2:$D$601) -> 27696.722 | D6: =SUMIF(Monthly!$B$2:$B$601,A6,Monthly!$E$2:$E$601) -> 5145.4671 | E6: =AVERAGEIF(Monthly!$B$2:$B$601,A6,Monthly!$C$2:$C$601) -> 380449.48 | F6: =C6*IF(E6<=Inputs!$B$46,1,Inputs!$B$46/E6) -> 27696.722 | G6: =Inputs!$B$12*IF(Inputs!$B$35="",AC5,MIN(AC5,Inputs!$B$7*(1+Inputs!$B$35)^(A6-1))) -> 5264.3635 | H6: =Inputs!$B$55 -> 10000 | I6: =Inputs!$B$44*(1+Inputs!$B$22)^A6 -> 36967.616 | J6: =F6+MIN(H6,G6+Inputs!$B$27)+Inputs!$B$28 -> 32961.086 | K6: =MIN(H6,Inputs!$B$27)+Inputs!$B$28 -> 0 | L6: =IF(J6>I6,"Yes","No") -> No | N6: =IF(Inputs!$B$25="Yes",Inputs!$B$26*(MAX(I6,J6)-MAX(I6,K6)),0) -> 0 | O6: =SUMIF(Monthly!$B$2:$B$601,A6,Monthly!$N$2:$N$601) -> 46482.496 | P6: =SUMIF(Monthly!$B$2:$B$601,A6,Monthly!$O$2:$O$601) -> 34626.713 | Q6: =AC6 -> 608326.45 | R6: =INDEX(Monthly!$F$2:$F$601,A6*12) -> 377631.45 | S6: =Q6*Inputs!$B$23 -> 36499.587 | T6: =MAX(0,Q6-S6-(Inputs!$B$7+Inputs!$B$40)-IF(A6>=2,Inputs!$B$45,0))*Inputs!$B$29 -> 0 | U6: =INDEX(Monthly!$S$2:$S$601,A6*12)-Inputs!$B$29*MAX(0,INDEX(Monthly!$S$2:$S$601,A6*12)-INDEX(Monthly!$T$2:$T$601,A6*12)) -> 0 | V6: =Q6-S6-R6-T6+U6 -> 194195.41 | W6: =INDEX(Monthly!$Q$2:$Q$601,A6*12)-Inputs!$B$29*MAX(0,INDEX(Monthly!$Q$2:$Q$601,A6*12)-INDEX(Monthly!$R$2:$R$601,A6*12)) -> 228229 | X6: =V6-W6 -> -34033.593 | Y6: =(1+Inputs!$B$22)^A6 -> 1.1480626 | Z6: =X6/Y6 -> -29644.371 | AA6: =IF(AND(X6>=0,COUNTIF(X6:X$51,"<0")=0),A6,"") | AB6: =IF(Inputs!$B$32="Revert",(1+Inputs!$B$18)*EXP(LN(1+Inputs!$B$33)*(0.5^(A6/Inputs!$B$34)-0.5^((A6-1)/Inputs!$B$34)))-1,Inputs!$B$20) -> 0.04 | AC6: =AC5*(1+AB6) -> 608326.45
A7: 6 | B7: =TEXT(2026+A7,"0") -> 2032 | C7: =SUMIF(Monthly!$B$2:$B$601,A7,Monthly!$D$2:$D$601) -> 27309.377 | D7: =SUMIF(Monthly!$B$2:$B$601,A7,Monthly!$E$2:$E$601) -> 5532.8122 | E7: =AVERAGEIF(Monthly!$B$2:$B$601,A7,Monthly!$C$2:$C$601) -> 375128.81 | F7: =C7*IF(E7<=Inputs!$B$46,1,Inputs!$B$46/E7) -> 27309.377 | G7: =Inputs!$B$12*IF(Inputs!$B$35="",AC6,MIN(AC6,Inputs!$B$7*(1+Inputs!$B$35)^(A7-1))) -> 5474.9381 | H7: =Inputs!$B$55 -> 10000 | I7: =Inputs!$B$44*(1+Inputs!$B$22)^A7 -> 38002.709 | J7: =F7+MIN(H7,G7+Inputs!$B$27)+Inputs!$B$28 -> 32784.315 | K7: =MIN(H7,Inputs!$B$27)+Inputs!$B$28 -> 0 | L7: =IF(J7>I7,"Yes","No") -> No | N7: =IF(Inputs!$B$25="Yes",Inputs!$B$26*(MAX(I7,J7)-MAX(I7,K7)),0) -> 0 | O7: =SUMIF(Monthly!$B$2:$B$601,A7,Monthly!$N$2:$N$601) -> 46927.597 | P7: =SUMIF(Monthly!$B$2:$B$601,A7,Monthly!$O$2:$O$601) -> 35837.24 | Q7: =AC7 -> 632659.51 | R7: =INDEX(Monthly!$F$2:$F$601,A7*12) -> 372098.64 | S7: =Q7*Inputs!$B$23 -> 37959.571 | T7: =MAX(0,Q7-S7-(Inputs!$B$7+Inputs!$B$40)-IF(A7>=2,Inputs!$B$45,0))*Inputs!$B$29 -> 0 | U7: =INDEX(Monthly!$S$2:$S$601,A7*12)-Inputs!$B$29*MAX(0,INDEX(Monthly!$S$2:$S$601,A7*12)-INDEX(Monthly!$T$2:$T$601,A7*12)) -> 0 | V7: =Q7-S7-R7-T7+U7 -> 222601.3 | W7: =INDEX(Monthly!$Q$2:$Q$601,A7*12)-Inputs!$B$29*MAX(0,INDEX(Monthly!$Q$2:$Q$601,A7*12)-INDEX(Monthly!$R$2:$R$601,A7*12)) -> 253620.76 | X7: =V7-W7 -> -31019.46 | Y7: =(1+Inputs!$B$22)^A7 -> 1.1802084 | Z7: =X7/Y7 -> -26283.037 | AA7: =IF(AND(X7>=0,COUNTIF(X7:X$51,"<0")=0),A7,"") | AB7: =IF(Inputs!$B$32="Revert",(1+Inputs!$B$18)*EXP(LN(1+Inputs!$B$33)*(0.5^(A7/Inputs!$B$34)-0.5^((A7-1)/Inputs!$B$34)))-1,Inputs!$B$20) -> 0.04 | AC7: =AC6*(1+AB7) -> 632659.51
A8: 7 | B8: =TEXT(2026+A8,"0") -> 2033 | C8: =SUMIF(Monthly!$B$2:$B$601,A8,Monthly!$D$2:$D$601) -> 26892.873 | D8: =SUMIF(Monthly!$B$2:$B$601,A8,Monthly!$E$2:$E$601) -> 5949.3161 | E8: =AVERAGEIF(Monthly!$B$2:$B$601,A8,Monthly!$C$2:$C$601) -> 369407.6 | F8: =C8*IF(E8<=Inputs!$B$46,1,Inputs!$B$46/E8) -> 26892.873 | G8: =Inputs!$B$12*IF(Inputs!$B$35="",AC7,MIN(AC7,Inputs!$B$7*(1+Inputs!$B$35)^(A8-1))) -> 5693.9356 | H8: =Inputs!$B$55 -> 10000 | I8: =Inputs!$B$44*(1+Inputs!$B$22)^A8 -> 39066.785 | J8: =F8+MIN(H8,G8+Inputs!$B$27)+Inputs!$B$28 -> 32586.809 | K8: =MIN(H8,Inputs!$B$27)+Inputs!$B$28 -> 0 | L8: =IF(J8>I8,"Yes","No") -> No | N8: =IF(Inputs!$B$25="Yes",Inputs!$B$26*(MAX(I8,J8)-MAX(I8,K8)),0) -> 0 | O8: =SUMIF(Monthly!$B$2:$B$601,A8,Monthly!$N$2:$N$601) -> 47387.688 | P8: =SUMIF(Monthly!$B$2:$B$601,A8,Monthly!$O$2:$O$601) -> 37090.097 | Q8: =AC8 -> 657965.89 | R8: =INDEX(Monthly!$F$2:$F$601,A8*12) -> 366149.32 | S8: =Q8*Inputs!$B$23 -> 39477.953 | T8: =MAX(0,Q8-S8-(Inputs!$B$7+Inputs!$B$40)-IF(A8>=2,Inputs!$B$45,0))*Inputs!$B$29 -> 0 | U8: =INDEX(Monthly!$S$2:$S$601,A8*12)-Inputs!$B$29*MAX(0,INDEX(Monthly!$S$2:$S$601,A8*12)-INDEX(Monthly!$T$2:$T$601,A8*12)) -> 0 | V8: =Q8-S8-R8-T8+U8 -> 252338.61 | W8: =INDEX(Monthly!$Q$2:$Q$601,A8*12)-Inputs!$B$29*MAX(0,INDEX(Monthly!$Q$2:$Q$601,A8*12)-INDEX(Monthly!$R$2:$R$601,A8*12)) -> 279833.78 | X8: =V8-W8 -> -27495.172 | Y8: =(1+Inputs!$B$22)^A8 -> 1.2132542 | Z8: =X8/Y8 -> -22662.334 | AA8: =IF(AND(X8>=0,COUNTIF(X8:X$51,"<0")=0),A8,"") | AB8: =IF(Inputs!$B$32="Revert",(1+Inputs!$B$18)*EXP(LN(1+Inputs!$B$33)*(0.5^(A8/Inputs!$B$34)-0.5^((A8-1)/Inputs!$B$34)))-1,Inputs!$B$20) -> 0.04 | AC8: =AC7*(1+AB8) -> 657965.89
A9: 8 | B9: =TEXT(2026+A9,"0") -> 2034 | C9: =SUMIF(Monthly!$B$2:$B$601,A9,Monthly!$D$2:$D$601) -> 26445.015 | D9: =SUMIF(Monthly!$B$2:$B$601,A9,Monthly!$E$2:$E$601) -> 6397.1741 | E9: =AVERAGEIF(Monthly!$B$2:$B$601,A9,Monthly!$C$2:$C$601) -> 363255.71 | F9: =C9*IF(E9<=Inputs!$B$46,1,Inputs!$B$46/E9) -> 26445.015 | G9: =Inputs!$B$12*IF(Inputs!$B$35="",AC8,MIN(AC8,Inputs!$B$7*(1+Inputs!$B$35)^(A9-1))) -> 5921.693 | H9: =Inputs!$B$55 -> 10000 | I9: =Inputs!$B$44*(1+Inputs!$B$22)^A9 -> 40160.655 | J9: =F9+MIN(H9,G9+Inputs!$B$27)+Inputs!$B$28 -> 32366.708 | K9: =MIN(H9,Inputs!$B$27)+Inputs!$B$28 -> 0 | L9: =IF(J9>I9,"Yes","No") -> No | N9: =IF(Inputs!$B$25="Yes",Inputs!$B$26*(MAX(I9,J9)-MAX(I9,K9)),0) -> 0 | O9: =SUMIF(Monthly!$B$2:$B$601,A9,Monthly!$N$2:$N$601) -> 47863.289 | P9: =SUMIF(Monthly!$B$2:$B$601,A9,Monthly!$O$2:$O$601) -> 38386.764 | Q9: =AC9 -> 684284.53 | R9: =INDEX(Monthly!$F$2:$F$601,A9*12) -> 359752.15 | S9: =Q9*Inputs!$B$23 -> 41057.072 | T9: =MAX(0,Q9-S9-(Inputs!$B$7+Inputs!$B$40)-IF(A9>=2,Inputs!$B$45,0))*Inputs!$B$29 -> 0 | U9: =INDEX(Monthly!$S$2:$S$601,A9*12)-Inputs!$B$29*MAX(0,INDEX(Monthly!$S$2:$S$601,A9*12)-INDEX(Monthly!$T$2:$T$601,A9*12)) -> 0 | V9: =Q9-S9-R9-T9+U9 -> 283475.3 | W9: =INDEX(Monthly!$Q$2:$Q$601,A9*12)-Inputs!$B$29*MAX(0,INDEX(Monthly!$Q$2:$Q$601,A9*12)-INDEX(Monthly!$R$2:$R$601,A9*12)) -> 306902.04 | X9: =V9-W9 -> -23426.735 | Y9: =(1+Inputs!$B$22)^A9 -> 1.2472253 | Z9: =X9/Y9 -> -18783.082 | AA9: =IF(AND(X9>=0,COUNTIF(X9:X$51,"<0")=0),A9,"") | AB9: =IF(Inputs!$B$32="Revert",(1+Inputs!$B$18)*EXP(LN(1+Inputs!$B$33)*(0.5^(A9/Inputs!$B$34)-0.5^((A9-1)/Inputs!$B$34)))-1,Inputs!$B$20) -> 0.04 | AC9: =AC8*(1+AB9) -> 684284.53
A10: 9 | B10: =TEXT(2026+A10,"0") -> 2035 | C10: =SUMIF(Monthly!$B$2:$B$601,A10,Monthly!$D$2:$D$601) -> 25963.443 | D10: =SUMIF(Monthly!$B$2:$B$601,A10,Monthly!$E$2:$E$601) -> 6878.7463 | E10: =AVERAGEIF(Monthly!$B$2:$B$601,A10,Monthly!$C$2:$C$601) -> 356640.7 | F10: =C10*IF(E10<=Inputs!$B$46,1,Inputs!$B$46/E10) -> 25963.443 | G10: =Inputs!$B$12*IF(Inputs!$B$35="",AC9,MIN(AC9,Inputs!$B$7*(1+Inputs!$B$35)^(A10-1))) -> 6158.5607 | H10: =Inputs!$B$55 -> 10000 | I10: =Inputs!$B$44*(1+Inputs!$B$22)^A10 -> 41285.153 | J10: =F10+MIN(H10,G10+Inputs!$B$27)+Inputs!$B$28 -> 32122.004 | K10: =MIN(H10,Inputs!$B$27)+Inputs!$B$28 -> 0 | L10: =IF(J10>I10,"Yes","No") -> No | N10: =IF(Inputs!$B$25="Yes",Inputs!$B$26*(MAX(I10,J10)-MAX(I10,K10)),0) -> 0 | O10: =SUMIF(Monthly!$B$2:$B$601,A10,Monthly!$N$2:$N$601) -> 48354.94 | P10: =SUMIF(Monthly!$B$2:$B$601,A10,Monthly!$O$2:$O$601) -> 39728.772 | Q10: =AC10 -> 711655.91 | R10: =INDEX(Monthly!$F$2:$F$601,A10*12) -> 352873.4 | S10: =Q10*Inputs!$B$23 -> 42699.354 | T10: =MAX(0,Q10-S10-(Inputs!$B$7+Inputs!$B$40)-IF(A10>=2,Inputs!$B$45,0))*Inputs!$B$29 -> 0 | U10: =INDEX(Monthly!$S$2:$S$601,A10*12)-Inputs!$B$29*MAX(0,INDEX(Monthly!$S$2:$S$601,A10*12)-INDEX(Monthly!$T$2:$T$601,A10*12)) -> 0 | V10: =Q10-S10-R10-T10+U10 -> 316083.15 | W10: =INDEX(Monthly!$Q$2:$Q$601,A10*12)-Inputs!$B$29*MAX(0,INDEX(Monthly!$Q$2:$Q$601,A10*12)-INDEX(Monthly!$R$2:$R$601,A10*12)) -> 334861.02 | X10: =V10-W10 -> -18777.877 | Y10: =(1+Inputs!$B$22)^A10 -> 1.2821476 | Z10: =X10/Y10 -> -14645.643 | AA10: =IF(AND(X10>=0,COUNTIF(X10:X$51,"<0")=0),A10,"") | AB10: =IF(Inputs!$B$32="Revert",(1+Inputs!$B$18)*EXP(LN(1+Inputs!$B$33)*(0.5^(A10/Inputs!$B$34)-0.5^((A10-1)/Inputs!$B$34)))-1,Inputs!$B$20) -> 0.04 | AC10: =AC9*(1+AB10) -> 711655.91
A11: 10 | B11: =TEXT(2026+A11,"0") -> 2036 | C11: =SUMIF(Monthly!$B$2:$B$601,A11,Monthly!$D$2:$D$601) -> 25445.619 | D11: =SUMIF(Monthly!$B$2:$B$601,A11,Monthly!$E$2:$E$601) -> 7396.5707 | E11: =AVERAGEIF(Monthly!$B$2:$B$601,A11,Monthly!$C$2:$C$601) -> 349527.73 | F11: =C11*IF(E11<=Inputs!$B$46,1,Inputs!$B$46/E11) -> 25445.619 | G11: =Inputs!$B$12*IF(Inputs!$B$35="",AC10,MIN(AC10,Inputs!$B$7*(1+Inputs!$B$35)^(A11-1))) -> 6404.9032 | H11: =Inputs!$B$55 -> 10000 | I11: =Inputs!$B$44*(1+Inputs!$B$22)^A11 -> 42441.138 | J11: =F11+MIN(H11,G11+Inputs!$B$27)+Inputs!$B$28 -> 31850.522 | K11: =MIN(H11,Inputs!$B$27)+Inputs!$B$28 -> 0 | L11: =IF(J11>I11,"Yes","No") -> No | N11: =IF(Inputs!$B$25="Yes",Inputs!$B$26*(MAX(I11,J11)-MAX(I11,K11)),0) -> 0 | O11: =SUMIF(Monthly!$B$2:$B$601,A11,Monthly!$N$2:$N$601) -> 48863.2 | P11: =SUMIF(Monthly!$B$2:$B$601,A11,Monthly!$O$2:$O$601) -> 41117.707 | Q11: =AC11 -> 740122.14 | R11: =INDEX(Monthly!$F$2:$F$601,A11*12) -> 345476.83 | S11: =Q11*Inputs!$B$23 -> 44407.329 | T11: =MAX(0,Q11-S11-(Inputs!$B$7+Inputs!$B$40)-IF(A11>=2,Inputs!$B$45,0))*Inputs!$B$29 -> 0 | U11: =INDEX(Monthly!$S$2:$S$601,A11*12)-Inputs!$B$29*MAX(0,INDEX(Monthly!$S$2:$S$601,A11*12)-INDEX(Monthly!$T$2:$T$601,A11*12)) -> 0 | V11: =Q11-S11-R11-T11+U11 -> 350237.98 | W11: =INDEX(Monthly!$Q$2:$Q$601,A11*12)-Inputs!$B$29*MAX(0,INDEX(Monthly!$Q$2:$Q$601,A11*12)-INDEX(Monthly!$R$2:$R$601,A11*12)) -> 363747.87 | X11: =V11-W11 -> -13509.891 | Y11: =(1+Inputs!$B$22)^A11 -> 1.3180478 | Z11: =X11/Y11 -> -10249.925 | AA11: =IF(AND(X11>=0,COUNTIF(X11:X$51,"<0")=0),A11,"") | AB11: =IF(Inputs!$B$32="Revert",(1+Inputs!$B$18)*EXP(LN(1+Inputs!$B$33)*(0.5^(A11/Inputs!$B$34)-0.5^((A11-1)/Inputs!$B$34)))-1,Inputs!$B$20) -> 0.04 | AC11: =AC10*(1+AB11) -> 740122.14
A12: 11 | B12: =TEXT(2026+A12,"0") -> 2037 | C12: =SUMIF(Monthly!$B$2:$B$601,A12,Monthly!$D$2:$D$601) -> 24888.813 | D12: =SUMIF(Monthly!$B$2:$B$601,A12,Monthly!$E$2:$E$601) -> 7953.3763 | E12: =AVERAGEIF(Monthly!$B$2:$B$601,A12,Monthly!$C$2:$C$601) -> 341879.3 | F12: =C12*IF(E12<=Inputs!$B$46,1,Inputs!$B$46/E12) -> 24888.813 | G12: =Inputs!$B$12*IF(Inputs!$B$35="",AC11,MIN(AC11,Inputs!$B$7*(1+Inputs!$B$35)^(A12-1))) -> 6661.0993 | H12: =Inputs!$B$55 -> 10000 | I12: =Inputs!$B$44*(1+Inputs!$B$22)^A12 -> 43629.49 | J12: =F12+MIN(H12,G12+Inputs!$B$27)+Inputs!$B$28 -> 31549.913 | K12: =MIN(H12,Inputs!$B$27)+Inputs!$B$28 -> 0 | L12: =IF(J12>I12,"Yes","No") -> No | N12: =IF(Inputs!$B$25="Yes",Inputs!$B$26*(MAX(I12,J12)-MAX(I12,K12)),0) -> 0 | O12: =SUMIF(Monthly!$B$2:$B$601,A12,Monthly!$N$2:$N$601) -> 49388.647 | P12: =SUMIF(Monthly!$B$2:$B$601,A12,Monthly!$O$2:$O$601) -> 42555.211 | Q12: =AC12 -> 769727.03 | R12: =INDEX(Monthly!$F$2:$F$601,A12*12) -> 337523.46 | S12: =Q12*Inputs!$B$23 -> 46183.622 | T12: =MAX(0,Q12-S12-(Inputs!$B$7+Inputs!$B$40)-IF(A12>=2,Inputs!$B$45,0))*Inputs!$B$29 -> 0 | U12: =INDEX(Monthly!$S$2:$S$601,A12*12)-Inputs!$B$29*MAX(0,INDEX(Monthly!$S$2:$S$601,A12*12)-INDEX(Monthly!$T$2:$T$601,A12*12)) -> 0 | V12: =Q12-S12-R12-T12+U12 -> 386019.95 | W12: =INDEX(Monthly!$Q$2:$Q$601,A12*12)-Inputs!$B$29*MAX(0,INDEX(Monthly!$Q$2:$Q$601,A12*12)-INDEX(Monthly!$R$2:$R$601,A12*12)) -> 393601.42 | X12: =V12-W12 -> -7581.4683 | Y12: =(1+Inputs!$B$22)^A12 -> 1.3549531 | Z12: =X12/Y12 -> -5595.3732 | AA12: =IF(AND(X12>=0,COUNTIF(X12:X$51,"<0")=0),A12,"") | AB12: =IF(Inputs!$B$32="Revert",(1+Inputs!$B$18)*EXP(LN(1+Inputs!$B$33)*(0.5^(A12/Inputs!$B$34)-0.5^((A12-1)/Inputs!$B$34)))-1,Inputs!$B$20) -> 0.04 | AC12: =AC11*(1+AB12) -> 769727.03
A13: 12 | B13: =TEXT(2026+A13,"0") -> 2038 | C13: =SUMIF(Monthly!$B$2:$B$601,A13,Monthly!$D$2:$D$601) -> 24290.092 | D13: =SUMIF(Monthly!$B$2:$B$601,A13,Monthly!$E$2:$E$601) -> 8552.0977 | E13: =AVERAGEIF(Monthly!$B$2:$B$601,A13,Monthly!$C$2:$C$601) -> 333655.11 | F13: =C13*IF(E13<=Inputs!$B$46,1,Inputs!$B$46/E13) -> 24290.092 | G13: =Inputs!$B$12*IF(Inputs!$B$35="",AC12,MIN(AC12,Inputs!$B$7*(1+Inputs!$B$35)^(A13-1))) -> 6927.5433 | H13: =Inputs!$B$55 -> 10000 | I13: =Inputs!$B$44*(1+Inputs!$B$22)^A13 -> 44851.115 | J13: =F13+MIN(H13,G13+Inputs!$B$27)+Inputs!$B$28 -> 31217.635 | K13: =MIN(H13,Inputs!$B$27)+Inputs!$B$28 -> 0 | L13: =IF(J13>I13,"Yes","No") -> No | N13: =IF(Inputs!$B$25="Yes",Inputs!$B$26*(MAX(I13,J13)-MAX(I13,K13)),0) -> 0 | O13: =SUMIF(Monthly!$B$2:$B$601,A13,Monthly!$N$2:$N$601) -> 49931.881 | P13: =SUMIF(Monthly!$B$2:$B$601,A13,Monthly!$O$2:$O$601) -> 44042.983 | Q13: =AC13 -> 800516.11 | R13: =INDEX(Monthly!$F$2:$F$601,A13*12) -> 328971.36 | S13: =Q13*Inputs!$B$23 -> 48030.967 | T13: =MAX(0,Q13-S13-(Inputs!$B$7+Inputs!$B$40)-IF(A13>=2,Inputs!$B$45,0))*Inputs!$B$29 -> 0 | U13: =INDEX(Monthly!$S$2:$S$601,A13*12)-Inputs!$B$29*MAX(0,INDEX(Monthly!$S$2:$S$601,A13*12)-INDEX(Monthly!$T$2:$T$601,A13*12)) -> 0 | V13: =Q13-S13-R13-T13+U13 -> 423513.78 | W13: =INDEX(Monthly!$Q$2:$Q$601,A13*12)-Inputs!$B$29*MAX(0,INDEX(Monthly!$Q$2:$Q$601,A13*12)-INDEX(Monthly!$R$2:$R$601,A13*12)) -> 424462.3 | X13: =V13-W13 -> -948.5156 | Y13: =(1+Inputs!$B$22)^A13 -> 1.3928918 | Z13: =X13/Y13 -> -680.96862 | AA13: =IF(AND(X13>=0,COUNTIF(X13:X$51,"<0")=0),A13,"") | AB13: =IF(Inputs!$B$32="Revert",(1+Inputs!$B$18)*EXP(LN(1+Inputs!$B$33)*(0.5^(A13/Inputs!$B$34)-0.5^((A13-1)/Inputs!$B$34)))-1,Inputs!$B$20) -> 0.04 | AC13: =AC12*(1+AB13) -> 800516.11
A14: 13 | B14: =TEXT(2026+A14,"0") -> 2039 | C14: =SUMIF(Monthly!$B$2:$B$601,A14,Monthly!$D$2:$D$601) -> 23646.299 | D14: =SUMIF(Monthly!$B$2:$B$601,A14,Monthly!$E$2:$E$601) -> 9195.8901 | E14: =AVERAGEIF(Monthly!$B$2:$B$601,A14,Monthly!$C$2:$C$601) -> 324811.81 | F14: =C14*IF(E14<=Inputs!$B$46,1,Inputs!$B$46/E14) -> 23646.299 | G14: =Inputs!$B$12*IF(Inputs!$B$35="",AC13,MIN(AC13,Inputs!$B$7*(1+Inputs!$B$35)^(A14-1))) -> 7204.645 | H14: =Inputs!$B$55 -> 10000 | I14: =Inputs!$B$44*(1+Inputs!$B$22)^A14 -> 46106.947 | J14: =F14+MIN(H14,G14+Inputs!$B$27)+Inputs!$B$28 -> 30850.944 | K14: =MIN(H14,Inputs!$B$27)+Inputs!$B$28 -> 0 | L14: =IF(J14>I14,"Yes","No") -> No | N14: =IF(Inputs!$B$25="Yes",Inputs!$B$26*(MAX(I14,J14)-MAX(I14,K14)),0) -> 0 | O14: =SUMIF(Monthly!$B$2:$B$601,A14,Monthly!$N$2:$N$601) -> 50493.523 | P14: =SUMIF(Monthly!$B$2:$B$601,A14,Monthly!$O$2:$O$601) -> 45582.78 | Q14: =AC14 -> 832536.75 | R14: =INDEX(Monthly!$F$2:$F$601,A14*12) -> 319775.47 | S14: =Q14*Inputs!$B$23 -> 49952.205 | T14: =MAX(0,Q14-S14-(Inputs!$B$7+Inputs!$B$40)-IF(A14>=2,Inputs!$B$45,0))*Inputs!$B$29 -> 0 | U14: =INDEX(Monthly!$S$2:$S$601,A14*12)-Inputs!$B$29*MAX(0,INDEX(Monthly!$S$2:$S$601,A14*12)-INDEX(Monthly!$T$2:$T$601,A14*12)) -> 0 | V14: =Q14-S14-R14-T14+U14 -> 462809.08 | W14: =INDEX(Monthly!$Q$2:$Q$601,A14*12)-Inputs!$B$29*MAX(0,INDEX(Monthly!$Q$2:$Q$601,A14*12)-INDEX(Monthly!$R$2:$R$601,A14*12)) -> 456373.04 | X14: =V14-W14 -> 6436.0369 | Y14: =(1+Inputs!$B$22)^A14 -> 1.4318928 | Z14: =X14/Y14 -> 4494.7758 | AA14: =IF(AND(X14>=0,COUNTIF(X14:X$51,"<0")=0),A14,"") -> 13 | AB14: =IF(Inputs!$B$32="Revert",(1+Inputs!$B$18)*EXP(LN(1+Inputs!$B$33)*(0.5^(A14/Inputs!$B$34)-0.5^((A14-1)/Inputs!$B$34)))-1,Inputs!$B$20) -> 0.04 | AC14: =AC13*(1+AB14) -> 832536.75
A15: 14 | B15: =TEXT(2026+A15,"0") -> 2040 | C15: =SUMIF(Monthly!$B$2:$B$601,A15,Monthly!$D$2:$D$601) -> 22954.043 | D15: =SUMIF(Monthly!$B$2:$B$601,A15,Monthly!$E$2:$E$601) -> 9888.1465 | E15: =AVERAGEIF(Monthly!$B$2:$B$601,A15,Monthly!$C$2:$C$601) -> 315302.79 | F15: =C15*IF(E15<=Inputs!$B$46,1,Inputs!$B$46/E15) -> 22954.043 | G15: =Inputs!$B$12*IF(Inputs!$B$35="",AC14,MIN(AC14,Inputs!$B$7*(1+Inputs!$B$35)^(A15-1))) -> 7492.8308 | H15: =Inputs!$B$55 -> 10000 | I15: =Inputs!$B$44*(1+Inputs!$B$22)^A15 -> 47397.941 | J15: =F15+MIN(H15,G15+Inputs!$B$27)+Inputs!$B$28 -> 30446.874 | K15: =MIN(H15,Inputs!$B$27)+Inputs!$B$28 -> 0 | L15: =IF(J15>I15,"Yes","No") -> No | N15: =IF(Inputs!$B$25="Yes",Inputs!$B$26*(MAX(I15,J15)-MAX(I15,K15)),0) -> 0 | O15: =SUMIF(Monthly!$B$2:$B$601,A15,Monthly!$N$2:$N$601) -> 51074.216 | P15: =SUMIF(Monthly!$B$2:$B$601,A15,Monthly!$O$2:$O$601) -> 47176.423 | Q15: =AC15 -> 865838.22 | R15: =INDEX(Monthly!$F$2:$F$601,A15*12) -> 309887.32 | S15: =Q15*Inputs!$B$23 -> 51950.293 | T15: =MAX(0,Q15-S15-(Inputs!$B$7+Inputs!$B$40)-IF(A15>=2,Inputs!$B$45,0))*Inputs!$B$29 -> 0 | U15: =INDEX(Monthly!$S$2:$S$601,A15*12)-Inputs!$B$29*MAX(0,INDEX(Monthly!$S$2:$S$601,A15*12)-INDEX(Monthly!$T$2:$T$601,A15*12)) -> 0 | V15: =Q15-S15-R15-T15+U15 -> 504000.61 | W15: =INDEX(Monthly!$Q$2:$Q$601,A15*12)-Inputs!$B$29*MAX(0,INDEX(Monthly!$Q$2:$Q$601,A15*12)-INDEX(Monthly!$R$2:$R$601,A15*12)) -> 489378.16 | X15: =V15-W15 -> 14622.443 | Y15: =(1+Inputs!$B$22)^A15 -> 1.4719857 | Z15: =X15/Y15 -> 9933.8211 | AA15: =IF(AND(X15>=0,COUNTIF(X15:X$51,"<0")=0),A15,"") -> 14 | AB15: =IF(Inputs!$B$32="Revert",(1+Inputs!$B$18)*EXP(LN(1+Inputs!$B$33)*(0.5^(A15/Inputs!$B$34)-0.5^((A15-1)/Inputs!$B$34)))-1,Inputs!$B$20) -> 0.04 | AC15: =AC14*(1+AB15) -> 865838.22
A16: 15 | B16: =TEXT(2026+A16,"0") -> 2041 | C16: =SUMIF(Monthly!$B$2:$B$601,A16,Monthly!$D$2:$D$601) -> 22209.674 | D16: =SUMIF(Monthly!$B$2:$B$601,A16,Monthly!$E$2:$E$601) -> 10632.515 | E16: =AVERAGEIF(Monthly!$B$2:$B$601,A16,Monthly!$C$2:$C$601) -> 305077.94 | F16: =C16*IF(E16<=Inputs!$B$46,1,Inputs!$B$46/E16) -> 22209.674 | G16: =Inputs!$B$12*IF(Inputs!$B$35="",AC15,MIN(AC15,Inputs!$B$7*(1+Inputs!$B$35)^(A16-1))) -> 7792.544 | H16: =Inputs!$B$55 -> 10000 | I16: =Inputs!$B$44*(1+Inputs!$B$22)^A16 -> 48725.083 | J16: =F16+MIN(H16,G16+Inputs!$B$27)+Inputs!$B$28 -> 30002.218 | K16: =MIN(H16,Inputs!$B$27)+Inputs!$B$28 -> 0 | L16: =IF(J16>I16,"Yes","No") -> No | N16: =IF(Inputs!$B$25="Yes",Inputs!$B$26*(MAX(I16,J16)-MAX(I16,K16)),0) -> 0 | O16: =SUMIF(Monthly!$B$2:$B$601,A16,Monthly!$N$2:$N$601) -> 51674.627 | P16: =SUMIF(Monthly!$B$2:$B$601,A16,Monthly!$O$2:$O$601) -> 48825.793 | Q16: =AC16 -> 900471.75 | R16: =INDEX(Monthly!$F$2:$F$601,A16*12) -> 299254.81 | S16: =Q16*Inputs!$B$23 -> 54028.305 | T16: =MAX(0,Q16-S16-(Inputs!$B$7+Inputs!$B$40)-IF(A16>=2,Inputs!$B$45,0))*Inputs!$B$29 -> 0 | U16: =INDEX(Monthly!$S$2:$S$601,A16*12)-Inputs!$B$29*MAX(0,INDEX(Monthly!$S$2:$S$601,A16*12)-INDEX(Monthly!$T$2:$T$601,A16*12)) -> 0 | V16: =Q16-S16-R16-T16+U16 -> 547188.64 | W16: =INDEX(Monthly!$Q$2:$Q$601,A16*12)-Inputs!$B$29*MAX(0,INDEX(Monthly!$Q$2:$Q$601,A16*12)-INDEX(Monthly!$R$2:$R$601,A16*12)) -> 523524.28 | X16: =V16-W16 -> 23664.363 | Y16: =(1+Inputs!$B$22)^A16 -> 1.5132013 | Z16: =X16/Y16 -> 15638.608 | AA16: =IF(AND(X16>=0,COUNTIF(X16:X$51,"<0")=0),A16,"") -> 15 | AB16: =IF(Inputs!$B$32="Revert",(1+Inputs!$B$18)*EXP(LN(1+Inputs!$B$33)*(0.5^(A16/Inputs!$B$34)-0.5^((A16-1)/Inputs!$B$34)))-1,Inputs!$B$20) -> 0.04 | AC16: =AC15*(1+AB16) -> 900471.75
... A51: 50 | B51: =TEXT(2026+A51,"0") -> 2076 | C51: =SUMIF(Monthly!$B$2:$B$601,A51,Monthly!$D$2:$D$601) -> 0 | D51: =SUMIF(Monthly!$B$2:$B$601,A51,Monthly!$E$2:$E$601) -> 0 | E51: =AVERAGEIF(Monthly!$B$2:$B$601,A51,Monthly!$C$2:$C$601) -> 1.286935e-10 | F51: =C51*IF(E51<=Inputs!$B$46,1,Inputs!$B$46/E51) -> 0 | G51: =Inputs!$B$12*IF(Inputs!$B$35="",AC50,MIN(AC50,Inputs!$B$7*(1+Inputs!$B$35)^(A51-1))) -> 30750.072 | H51: =Inputs!$B$55 -> 10000 | I51: =Inputs!$B$44*(1+Inputs!$B$22)^A51 -> 128088.93 | J51: =F51+MIN(H51,G51+Inputs!$B$27)+Inputs!$B$28 -> 10000 | K51: =MIN(H51,Inputs!$B$27)+Inputs!$B$28 -> 0 | L51: =IF(J51>I51,"Yes","No") -> No | N51: =IF(Inputs!$B$25="Yes",Inputs!$B$26*(MAX(I51,J51)-MAX(I51,K51)),0) -> 0 | O51: =SUMIF(Monthly!$B$2:$B$601,A51,Monthly!$N$2:$N$601) -> 59771.841 | P51: =SUMIF(Monthly!$B$2:$B$601,A51,Monthly!$O$2:$O$601) -> 162578.46 | Q51: =AC51 -> 3553341.7 | R51: =INDEX(Monthly!$F$2:$F$601,A51*12) -> 1.286935e-10 | S51: =Q51*Inputs!$B$23 -> 213200.5 | T51: =MAX(0,Q51-S51-(Inputs!$B$7+Inputs!$B$40)-IF(A51>=2,Inputs!$B$45,0))*Inputs!$B$29 -> 349146.18 | U51: =INDEX(Monthly!$S$2:$S$601,A51*12)-Inputs!$B$29*MAX(0,INDEX(Monthly!$S$2:$S$601,A51*12)-INDEX(Monthly!$T$2:$T$601,A51*12)) -> 3228347 | V51: =Q51-S51-R51-T51+U51 -> 6219342 | W51: =INDEX(Monthly!$Q$2:$Q$601,A51*12)-Inputs!$B$29*MAX(0,INDEX(Monthly!$Q$2:$Q$601,A51*12)-INDEX(Monthly!$R$2:$R$601,A51*12)) -> 5004747.4 | X51: =V51-W51 -> 1214594.5 | Y51: =(1+Inputs!$B$22)^A51 -> 3.9779171 | Z51: =X51/Y51 -> 305334.29 | AA51: =IF(AND(X51>=0,COUNTIF(X51:X$51,"<0")=0),A51,"") -> 50 | AB51: =IF(Inputs!$B$32="Revert",(1+Inputs!$B$18)*EXP(LN(1+Inputs!$B$33)*(0.5^(A51/Inputs!$B$34)-0.5^((A51-1)/Inputs!$B$34)))-1,Inputs!$B$20) -> 0.04 | AC51: =AC50*(1+AB51) -> 3553341.7

Sheet Sources
A1: Sources and Simplifications
A3: Mortgage Rates | B3: Freddie Mac PMMS, Oct 1, 2026: 30-yr 7.28%, 15-yr 6.60%. https://www.globenewswire.com/news-release/2026/10/01/3373202/0/en/mortgage-rates-average-7-28.html
A4: Home Prices | B4: FHFA All-Transactions HPI (FRED USSTHPI): 59.67 (1975Q1), 124.73 (1985Q1), 368.17 (2006Q1), 713.09 (2026Q1). https://fred.stlouisfed.org/series/USSTHPI ; Q2 2026 YoY +2.1%: https://www.fhfa.gov/news/news-release/u.s.-house-prices-rise-2.1-percent-year-over-year-up-0.3-percent-quarter-over-quarter
A5: Stock and Real Estate Returns | B5: NYU Stern (Damodaran), Historical Returns 1928-2025. $100 in S&P 500 at start of 1928 -> $1,157,599 end of 2025 (10.0%/yr); real estate series -> $5,626 (4.2%/yr). https://pages.stern.nyu.edu/~adamodar/New_Home_Page/datafile/histretSP.html
A6: Forward Stock Forecast | B6: Vanguard 2026 Economic and Market Outlook (Dec 10, 2025): US stocks ~4-5% over the next 5-10 years. https://corporate.vanguard.com/content/corporatesite/us/en/corp/who-we-are/pressroom/press-release-vanguard-releases-2026-economic-and-market-outlook-121025.html
A7: Rent Growth and Inflation | B7: BLS CPI via FRED, 1982-84 = 100. Rent of primary residence Jan 2026 = 441.718; all items Jan 2026 = 325.252. https://fred.stlouisfed.org/series/CUUR0000SEHA ; https://fred.stlouisfed.org/series/cpiaucns
A8: Property Tax | B8: NAHB, 2024 ACS: $370.0B taxes / $51.7T value = $8.88 per $1,000. https://eyeonhousing.org/2025/11/property-taxes-by-state-2024/
A9: Homeowners Insurance | B9: NAIC homeowners report, 2022 data (premiums +10.5% vs 2021). https://content.naic.org/index.php/article/naic-releases-homeowners-insurance-report-2022 . Default 0.5% of value is an estimate.
A10: Maintenance | B10: Harvard JCHS LIRA: owner improvement and repair spending ~$472B/yr. https://jchs.harvard.edu/blog/turn-growth-expected-residential-remodeling
A11: Closing Costs | B11: LodeStar 2026 Purchase Closing Cost Report: avg 1.04% of price excluding lender fees. https://www.lodestarss.com/?p=17088
A12: Dividend Yield | B12: Multpl (S&P data): S&P 500 dividend yield ~1.06% at end of Sep 2026, 1.15% at end of 2025. https://www.multpl.com/s-p-500-dividend-yield/table/by-year
A13: Selling Costs | B13: Federal Reserve FEDS Note, May 12, 2025: buyer-agent commissions fell from ~3% (late 1990s) to ~2.7%; seller side not observed but likely similar; data through 2023. https://www.federalreserve.gov/econres/notes/feds-notes/commissions-and-omissions-trends-in-real-estate-broker-compensation-20250512.html
A14: PMI | B14: Urban Institute Housing Finance Policy Center range 0.46%-1.5% of loan/yr (reported by Experian). https://www.experian.com/blogs/ask-experian/how-much-does-private-mortgage-insurance-pmi-cost
... A29: Method | B29: Both households spend the same total each month. The cheaper side invests the difference monthly at the investment return. On day one the renter invests the down payment plus closing costs.

Sheet Presets
A1: Scenario Presets (Selected on the Inputs Sheet)
A3: Markets
A4: Market | B4: Median Listing Price | C4: HUD 3-Bed Rent | D4: Property Tax | E4: Assessment Cap | F4: Price-to-Rent vs Norm | G4: Rent Growth (1990-2025) | H4: Price Growth (1990-2025) | I4: Basis
A5: Custom (Use My Inputs)
A6: Atlanta, GA | B6: 387000 | C6: 2182 | D6: 0.00767 | F6: 0.2898 | G6: 0.0322 | H6: 0.0424 | I6: Georgia effective rate 0.77%. FHFA's Atlanta price index ends in 2024, so its history runs through 2024.
A7: Boston, MA | B7: 844600 | C7: 3526 | D7: 0.00948 | F7: 0.3108 | G7: 0.0325 | H7: 0.0441 | I7: Massachusetts effective rate 0.95%; towns vary widely.
A8: Chicago, IL | B8: 438600 | C8: 2294 | D8: 0.01793 | F8: 0.0292 | G8: 0.0329 | H8: 0.0346 | I8: Illinois effective rate 1.79%, the highest in the country.
A9: Dallas, TX | B9: 380100 | C9: 2431 | D9: 0.01245 | E9: 0.1 | F9: 0.3461 | G9: 0.0343 | H9: 0.0437 | I9: Texas effective rate 1.25%; new buyers usually pay more. Homestead appraisal increases capped at 10% a year.
A10: Denver, CO | B10: 668300 | C10: 2734 | D10: 0.00519 | F10: 0.4022 | G10: 0.0391 | H10: 0.0565 | I10: Colorado effective rate 0.52%.
A11: Detroit, MI | B11: 311800 | C11: 1724 | D11: 0.01129 | E11: 0.028 | F11: 0.1363 | G11: 0.0278 | H11: 0.0359 | I11: Michigan effective rate 1.13%. Proposal A caps taxable value growth at 5% or inflation, whichever is lower (2.7% for 2026), until a sale; set to the model's 2.8% inflation.
A12: Honolulu, HI | B12: 1190000 | C12: 3674 | D12: 0.0032 | F12: 0.2674 | G12: 0.0293 | H12: 0.0379 | I12: Price is the Honolulu Board of Realtors' Oahu single-family median for January to August 2026 ($1.19M; August alone was $1.24M). Tax: the owner-occupied rate is $3.50 per $1,000 after a $120,000 home exemption ($140,000 from July 2027), about 0.32% effective, with no assessment cap. Hawaii adds a seller-paid conveyance tax of 0.3% to 0.5% at these prices, so raise selling costs to about 6.4%. Condos run far cheaper (median $510,000) but carry high HOA and insurance costs.
A13: Houston, TX | B13: 345200 | C13: 2116 | D13: 0.01245 | E13: 0.1 | F13: 0.3415 | G13: 0.0339 | H13: 0.0426 | I13: Texas effective rate 1.25%; new buyers usually pay more. Homestead appraisal increases capped at 10% a year.
A14: Los Angeles, CA | B14: 879900 | C14: 3298 | D14: 0.0115 | E14: 0.02 | F14: 0.3512 | G14: 0.0342 | H14: 0.043 | I14: 1% of purchase price plus voter-approved bonds (about 1.15% all-in for a new buyer); Prop 13 caps assessment growth at 2% a year. Check for Mello-Roos in newer suburbs.
A15: Miami, FL | B15: 659000 | C15: 3127 | D15: 0.0076 | E15: 0.028 | F15: 0.5507 | G15: 0.0409 | H15: 0.061 | I15: Florida effective rate 0.76%. Save Our Homes caps homestead assessment growth at 3% or inflation, whichever is lower; set to the model's 2.8% inflation. Florida is considering further homestead changes in 2026.
A16: Minneapolis, MN | B16: 414300 | C16: 2262 | D16: 0.00987 | F16: 0.1864 | G16: 0.0296 | H16: 0.0417 | I16: Minnesota effective rate 0.99%.
A17: New York, NY | B17: 802400 | C17: 3644 | D17: 0.01227 | F17: 0.2595 | G17: 0.0341 | H17: 0.0411 | I17: New York effective rate 1.23%. New York City has its own class 1 assessment caps (not modeled).
A18: Philadelphia, PA | B18: 419800 | C18: 2170 | D18: 0.01137 | F18: 0.3458 | G18: 0.029 | H18: 0.0401 | I18: Pennsylvania effective rate 1.14%.
A19: San Diego, CA | B19: 1075000 | C19: 3998 | D19: 0.0115 | E19: 0.02 | F19: 0.2936 | G19: 0.0374 | H19: 0.0474 | I19: 1% of purchase price plus voter-approved bonds (about 1.15% all-in for a new buyer); Prop 13 caps assessment growth at 2% a year. Check for Mello-Roos in newer suburbs.
A20: San Francisco, CA | B20: 1500000 | C20: 4604 | D20: 0.0115 | E20: 0.02 | F20: 0.2261 | G20: 0.036 | H20: 0.0438 | I20: 1% of purchase price plus voter-approved bonds (about 1.15% all-in for a new buyer); Prop 13 caps assessment growth at 2% a year. Check for Mello-Roos in newer suburbs.
A21: St. Louis, MO | B21: 314100 | C21: 1568 | D21: 0.00849 | F21: 0.1983 | G21: 0.0261 | H21: 0.036 | I21: Missouri effective rate 0.85%.
A22: Tampa, FL | B22: 415000 | C22: 2527 | D22: 0.0076 | E22: 0.028 | F22: 0.4243 | G22: 0.039 | H22: 0.0536 | I22: Florida effective rate 0.76%. Save Our Homes caps homestead assessment growth at 3% or inflation, whichever is lower; set to the model's 2.8% inflation. Florida is considering further homestead changes in 2026.
A23: Washington, DC (Arlington, Fairfax) | B23: 688200 | C23: 2835 | D23: 0.0112 | F23: 0.2191 | G23: 0.0344 | H23: 0.0504 | I23: Fairfax County rate $1.12 per $100 (Arlington, Alexandria and Maryland suburbs differ). Rent history spliced across a 2018 BLS change; baseline 1997-2018.
A31: Home Price Paths
A32: Path | B32: Mode | C32: Half-Life (Years) | D32: Basis
A33: Custom (Use My Inputs) | D33: Uses your column E values.
A34: Prices Track Rents | B34: Fixed | D34: Appreciation equals rent growth; today's price-to-rent ratio holds.
A35: Local Historical Trend | B35: Fixed | D35: Appreciation equals the market's 1990-2025 FHFA price growth; bakes in the ratio's rise over that period.
A36: Slow Reversion (Half-Life 24 Years) | B36: Revert | C36: 24 | D36: Pooled estimate across 18 metros, 1990-2025 data incl. the 2020s run-up (90% range about 18 to 39 years).
A37: Typical Reversion (Half-Life 11 Years) | B37: Revert | C37: 11 | D37: Same 18-metro estimate on 1990-2019 data, before the 2020s boom (90% range about 9 to 13 years).
A38: Fast Reversion (Half-Life 2 Years) | B38: Revert | C38: 2 | D38: The 2000s bust pace: price-to-rent fell peak to trough in 4 to 8 years (median 6) across 19 metros.
A41: Investment Return
A42: Scenario | B42: Return | C42: Basis
A43: Custom (Use My Inputs) | C43: Uses your column E value.
A44: Conservative: 5% (Vanguard 10-Year Forecast) | B44: 0.05 | C44: Vanguard's 10-year US stock forecast: about 4% to 6% a year across its 2026 updates.
A45: Moderate: 7% (Between Forecast and History) | B45: 0.07 | C45: Midpoint between today's forecasts and long-run history.
A46: Historical: 10% (S&P 500 Since 1928) | B46: 0.1 | C46: S&P 500 average, 1928-2025 (NYU Stern, Damodaran).
